<?xml version="1.0" ?>
<root>
    <agent start_id="501" goal_id="829"/>
    <agent start_id="404" goal_id="604"/>
    <agent start_id="381" goal_id="278"/>
    <agent start_id="28" goal_id="727"/>
    <agent start_id="845" goal_id="287"/>
    <agent start_id="432" goal_id="304"/>
    <agent start_id="558" goal_id="419"/>
    <agent start_id="532" goal_id="102"/>
    <agent start_id="462" goal_id="807"/>
    <agent start_id="182" goal_id="637"/>
    <agent start_id="545" goal_id="608"/>
    <agent start_id="442" goal_id="134"/>
    <agent start_id="397" goal_id="462"/>
    <agent start_id="575" goal_id="843"/>
    <agent start_id="5" goal_id="859"/>
    <agent start_id="345" goal_id="756"/>
    <agent start_id="131" goal_id="193"/>
    <agent start_id="313" goal_id="106"/>
    <agent start_id="169" goal_id="4"/>
    <agent start_id="261" goal_id="317"/>
    <agent start_id="651" goal_id="548"/>
    <agent start_id="428" goal_id="679"/>
    <agent start_id="461" goal_id="725"/>
    <agent start_id="289" goal_id="312"/>
    <agent start_id="598" goal_id="328"/>
    <agent start_id="15" goal_id="831"/>
    <agent start_id="295" goal_id="601"/>
    <agent start_id="409" goal_id="776"/>
    <agent start_id="174" goal_id="484"/>
    <agent start_id="107" goal_id="212"/>
    <agent start_id="646" goal_id="605"/>
    <agent start_id="735" goal_id="535"/>
    <agent start_id="712" goal_id="383"/>
    <agent start_id="56" goal_id="649"/>
    <agent start_id="666" goal_id="388"/>
    <agent start_id="595" goal_id="379"/>
    <agent start_id="185" goal_id="636"/>
    <agent start_id="335" goal_id="760"/>
    <agent start_id="744" goal_id="0"/>
    <agent start_id="13" goal_id="526"/>
    <agent start_id="209" goal_id="868"/>
    <agent start_id="663" goal_id="687"/>
    <agent start_id="613" goal_id="557"/>
    <agent start_id="230" goal_id="718"/>
    <agent start_id="82" goal_id="375"/>
    <agent start_id="611" goal_id="288"/>
    <agent start_id="421" goal_id="615"/>
    <agent start_id="390" goal_id="837"/>
    <agent start_id="34" goal_id="762"/>
    <agent start_id="219" goal_id="507"/>
    <agent start_id="7" goal_id="871"/>
    <agent start_id="243" goal_id="335"/>
    <agent start_id="168" goal_id="132"/>
    <agent start_id="275" goal_id="274"/>
    <agent start_id="218" goal_id="466"/>
    <agent start_id="730" goal_id="634"/>
    <agent start_id="479" goal_id="598"/>
    <agent start_id="143" goal_id="777"/>
    <agent start_id="605" goal_id="326"/>
    <agent start_id="655" goal_id="815"/>
    <agent start_id="216" goal_id="818"/>
    <agent start_id="553" goal_id="819"/>
    <agent start_id="180" goal_id="339"/>
    <agent start_id="154" goal_id="161"/>
    <agent start_id="772" goal_id="366"/>
    <agent start_id="374" goal_id="422"/>
    <agent start_id="265" goal_id="675"/>
    <agent start_id="291" goal_id="137"/>
    <agent start_id="439" goal_id="120"/>
    <agent start_id="436" goal_id="686"/>
    <agent start_id="867" goal_id="836"/>
    <agent start_id="873" goal_id="206"/>
    <agent start_id="465" goal_id="873"/>
    <agent start_id="229" goal_id="28"/>
    <agent start_id="264" goal_id="768"/>
    <agent start_id="379" goal_id="380"/>
    <agent start_id="203" goal_id="793"/>
    <agent start_id="57" goal_id="667"/>
    <agent start_id="410" goal_id="838"/>
    <agent start_id="476" goal_id="83"/>
    <agent start_id="66" goal_id="750"/>
    <log>
        <summary time="90.909066241999994" flowtime="2250.4171810661692" makespan="314.89144621719004"/>
        <agent number="0">
            <path duration="25.500000000000007">
                <section number="0" start_i="146.80000000000001" start_j="178.70000000000002" goal_i="158" goal_j="177.20000000000002" duration="11.299999999999988"/>
                <section number="1" start_i="158" start_j="177.20000000000002" goal_i="172.20000000000002" goal_j="177.20000000000002" duration="14.200000000000019"/>
            </path>
        </agent>
        <agent number="1">
            <path duration="89.916572695331155">
                <section number="0" start_i="223.20000000000002" start_j="98.900000000000006" goal_i="219.40000000000001" goal_j="87.5" duration="12.016655108639849"/>
                <section number="1" start_i="219.40000000000001" start_j="87.5" goal_i="213.10000000000002" goal_j="77.5" duration="11.819052415485761"/>
                <section number="2" start_i="213.10000000000002" start_j="77.5" goal_i="206" goal_j="68.600000000000009" duration="11.385077953180655"/>
                <section number="3" start_i="206" start_j="68.600000000000009" goal_i="199.40000000000001" goal_j="64.200000000000003" duration="7.9322128060207717"/>
                <section number="4" start_i="199.40000000000001" start_j="64.200000000000003" goal_i="191" goal_j="58.900000000000006" duration="9.932270636667127"/>
                <section number="5" start_i="191" start_j="58.900000000000006" goal_i="184" goal_j="47.700000000000003" duration="13.207573584879242"/>
                <section number="6" start_i="184" start_j="47.700000000000003" goal_i="188.70000000000002" goal_j="43.800000000000004" duration="6.1073725938410064"/>
                <section number="7" start_i="188.70000000000002" start_j="43.800000000000004" goal_i="192.5" goal_j="35" duration="9.5854055730574004"/>
                <section number="8" start_i="192.5" start_j="35" goal_i="200.40000000000001" goal_j="35.700000000000003" duration="7.9309520235593425"/>
            </path>
        </agent>
        <agent number="2">
            <path duration="181.86213455537279">
                <section number="0" start_i="153.90000000000001" start_j="92.400000000000006" goal_i="155.10000000000002" goal_j="108.60000000000001" duration="16.244383644817066"/>
                <section number="1" start_i="155.10000000000002" start_j="108.60000000000001" goal_i="156.80000000000001" goal_j="116.40000000000001" duration="7.9831071645068086"/>
                <section number="2" start_i="156.80000000000001" start_j="116.40000000000001" goal_i="161.70000000000002" goal_j="128.30000000000001" duration="12.869343417595168"/>
                <section number="3" start_i="161.70000000000002" start_j="128.30000000000001" goal_i="160.60000000000002" goal_j="136.20000000000002" duration="7.9762146410437111"/>
                <section number="4" start_i="160.60000000000002" start_j="136.20000000000002" goal_i="154.30000000000001" goal_j="140.5" duration="7.6275815302099517"/>
                <section number="5" start_i="154.30000000000001" start_j="140.5" goal_i="146.5" goal_j="156.20000000000002" duration="17.53082998605602"/>
                <section number="6" start_i="146.5" start_j="156.20000000000002" goal_i="116.80000000000001" goal_j="159.70000000000002" duration="29.905517885500657"/>
                <section number="7" start_i="116.80000000000001" start_j="159.70000000000002" goal_i="91" goal_j="163.30000000000001" duration="26.049952015310907"/>
                <section number="8" start_i="91" start_j="163.30000000000001" goal_i="80.5" goal_j="166.60000000000002" duration="11.0063617967065"/>
                <section number="9" start_i="80.5" start_j="166.60000000000002" goal_i="71" goal_j="165.70000000000002" duration="9.5425363504678273"/>
                <section number="10" start_i="71" start_j="165.70000000000002" goal_i="61.700000000000003" goal_j="166.20000000000002" duration="9.3134311615000342"/>
                <section number="11" start_i="61.700000000000003" start_j="166.20000000000002" goal_i="54.5" goal_j="169.30000000000001" duration="7.8390050389064072"/>
                <section number="12" start_i="54.5" start_j="169.30000000000001" goal_i="39" goal_j="178.40000000000001" duration="17.973869922751732"/>
            </path>
        </agent>
        <agent number="3">
            <path duration="131.73475395272683">
                <section number="0" start_i="103.60000000000001" start_j="84.700000000000003" goal_i="108.40000000000001" goal_j="83.200000000000003" duration="5.0289163842720601"/>
                <section number="1" start_i="108.40000000000001" start_j="83.200000000000003" goal_i="156.5" goal_j="118.10000000000001" duration="59.427434741876588"/>
                <section number="2" start_i="156.5" start_j="118.10000000000001" goal_i="161.70000000000002" goal_j="128.30000000000001" duration="11.44901742508938"/>
                <section number="3" start_i="161.70000000000002" start_j="128.30000000000001" goal_i="164.5" goal_j="141.40000000000001" duration="13.395894893585861"/>
                <section number="4" start_i="164.5" start_j="141.40000000000001" goal_i="172" goal_j="158.30000000000001" duration="18.489456454963744"/>
                <section number="5" start_i="172" start_j="158.30000000000001" goal_i="167.90000000000001" goal_j="174" duration="16.226521500309289"/>
                <section number="6" start_i="167.90000000000001" start_j="174" goal_i="171.90000000000001" goal_j="180.60000000000002" duration="7.7175125526299126"/>
            </path>
        </agent>
        <agent number="4">
            <path duration="143.69302899497885">
                <section number="0" start_i="168.80000000000001" start_j="39.900000000000006" goal_i="174.90000000000001" goal_j="40.700000000000003" duration="6.1522353661088038"/>
                <section number="1" start_i="174.90000000000001" start_j="40.700000000000003" goal_i="181.40000000000001" goal_j="48.300000000000004" duration="10.000499987500625"/>
                <section number="2" start_i="181.40000000000001" start_j="48.300000000000004" goal_i="182.10000000000002" goal_j="57.700000000000003" duration="9.4260277954183849"/>
                <section number="3" start_i="182.10000000000002" start_j="57.700000000000003" goal_i="182.70000000000002" goal_j="68.100000000000009" duration="10.41729331448434"/>
                <section number="4" start_i="182.70000000000002" start_j="68.100000000000009" goal_i="178.30000000000001" goal_j="95.700000000000003" duration="27.948524111301474"/>
                <section number="5" start_i="178.30000000000001" start_j="95.700000000000003" goal_i="177.60000000000002" goal_j="102" duration="6.3387695966961815"/>
                <section number="6" start_i="177.60000000000002" start_j="102" goal_i="175.90000000000001" goal_j="122.5" duration="20.570367036103178"/>
                <section number="7" start_i="175.90000000000001" start_j="122.5" goal_i="185.30000000000001" goal_j="147" duration="26.241379536906976"/>
                <section number="8" start_i="185.30000000000001" start_j="147" goal_i="200.10000000000002" goal_j="169.10000000000002" duration="26.597932250458882"/>
            </path>
        </agent>
        <agent number="5">
            <path duration="105.32369322619083">
                <section number="0" start_i="206" start_j="68.600000000000009" goal_i="198.20000000000002" goal_j="75.100000000000009" duration="10.153324578678637"/>
                <section number="1" start_i="198.20000000000002" start_j="75.100000000000009" goal_i="181.60000000000002" goal_j="78.5" duration="16.944615663980102"/>
                <section number="2" start_i="181.60000000000002" start_j="78.5" goal_i="117.30000000000001" goal_j="110.5" duration="71.822628746099241"/>
                <section number="3" start_i="117.30000000000001" start_j="110.5" goal_i="110.90000000000001" goal_j="110.7" duration="6.4031242374328485"/>
            </path>
        </agent>
        <agent number="6">
            <path duration="176.25674402735044">
                <section number="0" start_i="144.70000000000002" start_j="210.90000000000001" goal_i="133.30000000000001" goal_j="215.90000000000001" duration="12.448293055676354"/>
                <section number="1" start_i="133.30000000000001" start_j="215.90000000000001" goal_i="116.5" goal_j="217.40000000000001" duration="16.866831356244731"/>
                <section number="2" start_i="116.5" start_j="217.40000000000001" goal_i="101.7" goal_j="212.10000000000002" duration="15.720368952413288"/>
                <section number="3" start_i="101.7" start_j="212.10000000000002" goal_i="96.200000000000003" goal_j="205.5" duration="8.5912746434973357"/>
                <section number="4" start_i="96.200000000000003" start_j="205.5" goal_i="96.600000000000009" goal_j="181.10000000000002" duration="24.403278468271402"/>
                <section number="5" start_i="96.600000000000009" start_j="181.10000000000002" goal_i="96.5" goal_j="173.30000000000001" duration="7.8006409993025727"/>
                <section number="6" start_i="96.5" start_j="173.30000000000001" goal_i="108.7" goal_j="174.40000000000001" duration="12.249489785293108"/>
                <section number="7" start_i="108.7" start_j="174.40000000000001" goal_i="128.70000000000002" goal_j="172.90000000000001" duration="20.056171120131594"/>
                <section number="8" start_i="128.70000000000002" start_j="172.90000000000001" goal_i="156.10000000000002" goal_j="168.90000000000001" duration="27.690431560378414"/>
                <section number="9" start_i="156.10000000000002" start_j="168.90000000000001" goal_i="174" goal_j="168.90000000000001" duration="17.899999999999977"/>
                <section number="10" start_i="174" start_j="168.90000000000001" goal_i="185.40000000000001" goal_j="163.70000000000002" duration="12.529964086141661"/>
            </path>
        </agent>
        <agent number="7">
            <path duration="81.343028825645746">
                <section number="0" start_i="72.5" start_j="137.80000000000001" goal_i="74.299999999999997" goal_j="143.70000000000002" duration="6.1684682053164588"/>
                <section number="1" start_i="74.299999999999997" start_j="143.70000000000002" goal_i="77.100000000000009" goal_j="161.60000000000002" duration="18.117670931993448"/>
                <section number="2" start_i="77.100000000000009" start_j="161.60000000000002" goal_i="81" goal_j="178.10000000000002" duration="16.954645381133748"/>
                <section number="3" start_i="81" start_j="178.10000000000002" goal_i="79.600000000000009" goal_j="192.20000000000002" duration="14.169333082400165"/>
                <section number="4" start_i="79.600000000000009" start_j="192.20000000000002" goal_i="82.600000000000009" goal_j="206" duration="14.122322755127769"/>
                <section number="5" start_i="82.600000000000009" start_j="206" goal_i="87.600000000000009" goal_j="216.70000000000002" duration="11.810588469674158"/>
            </path>
        </agent>
        <agent number="8">
            <path duration="171.56492053519665">
                <section number="0" start_i="49.600000000000001" start_j="63.100000000000001" goal_i="53.600000000000001" goal_j="60.700000000000003" duration="4.6647615158762399"/>
                <section number="1" start_i="53.600000000000001" start_j="60.700000000000003" goal_i="68" goal_j="55" duration="15.487091398968367"/>
                <section number="2" start_i="68" start_j="55" goal_i="96.300000000000011" goal_j="53" duration="28.370583356709478"/>
                <section number="3" start_i="96.300000000000011" start_j="53" goal_i="107.2" goal_j="49.800000000000004" duration="11.360017605620151"/>
                <section number="4" start_i="107.2" start_j="49.800000000000004" goal_i="119.2" goal_j="46.800000000000004" duration="12.369316876852984"/>
                <section number="5" start_i="119.2" start_j="46.800000000000004" goal_i="131.40000000000001" goal_j="46.700000000000003" duration="12.200409829181964"/>
                <section number="6" start_i="131.40000000000001" start_j="46.700000000000003" goal_i="146.09999999999999" goal_j="45.400000000000006" duration="14.757371039585593"/>
                <section number="7" start_i="146.09999999999999" start_j="45.400000000000006" goal_i="160.30000000000001" goal_j="51.800000000000004" duration="15.57562197795005"/>
                <section number="8" start_i="160.30000000000001" start_j="51.800000000000004" goal_i="171.20000000000002" goal_j="58.400000000000006" duration="12.74244874425635"/>
                <section number="9" start_i="171.20000000000002" start_j="58.400000000000006" goal_i="179.10000000000002" goal_j="53.5" duration="9.296235797353674"/>
                <section number="10" start_i="179.10000000000002" start_j="53.5" goal_i="181.40000000000001" goal_j="48.300000000000004" duration="5.6859475903317787"/>
                <section number="11" start_i="181.40000000000001" start_j="48.300000000000004" goal_i="174.90000000000001" goal_j="40.700000000000003" duration="10.000499987500632"/>
                <section number="12" start_i="174.90000000000001" start_j="40.700000000000003" goal_i="170.90000000000001" goal_j="37" duration="5.4488530903301182"/>
                <section number="13" start_i="170.90000000000001" start_j="37" goal_i="162.30000000000001" goal_j="31.100000000000001" duration="10.429285689825548"/>
                <section number="14" start_i="162.30000000000001" start_j="31.100000000000001" goal_i="160.80000000000001" goal_j="28.300000000000001" duration="3.1764760348537209"/>
            </path>
        </agent>
        <agent number="9">
            <path duration="276.53158691908106">
                <section number="0" start_i="70.799999999999997" start_j="86.700000000000003" goal_i="84.5" goal_j="93.5" duration="15.29477034806342"/>
                <section number="1" start_i="84.5" start_j="93.5" goal_i="104.90000000000001" goal_j="93.900000000000006" duration="20.403921191770966"/>
                <section number="2" start_i="104.90000000000001" start_j="93.900000000000006" goal_i="120" goal_j="97.100000000000009" duration="15.435349040433124"/>
                <section number="3" start_i="120" start_j="97.100000000000009" goal_i="129.70000000000002" goal_j="102.7" duration="11.200446419674542"/>
                <section number="4" start_i="129.70000000000002" start_j="102.7" goal_i="142.59999999999999" goal_j="106.10000000000001" duration="13.340539719216743"/>
                <section number="5" start_i="142.59999999999999" start_j="106.10000000000001" goal_i="156.5" goal_j="118.10000000000001" duration="18.363278574372288"/>
                <section number="6" start_i="156.5" start_j="118.10000000000001" goal_i="161.70000000000002" goal_j="128.30000000000001" duration="11.44901742508938"/>
                <section number="7" start_i="161.70000000000002" start_j="128.30000000000001" goal_i="160.60000000000002" goal_j="136.20000000000002" duration="7.9762146410437111"/>
                <section number="8" start_i="160.60000000000002" start_j="136.20000000000002" goal_i="154.30000000000001" goal_j="140.5" duration="7.6275815302099517"/>
                <section number="9" start_i="154.30000000000001" start_j="140.5" goal_i="146.5" goal_j="156.20000000000002" duration="17.53082998605602"/>
                <section number="10" start_i="146.5" start_j="156.20000000000002" goal_i="116.80000000000001" goal_j="159.70000000000002" duration="29.905517885500643"/>
                <section number="11" start_i="116.80000000000001" start_j="159.70000000000002" goal_i="91" goal_j="163.30000000000001" duration="26.049952015310907"/>
                <section number="12" start_i="91" start_j="163.30000000000001" goal_i="80.5" goal_j="166.60000000000002" duration="11.0063617967065"/>
                <section number="13" start_i="80.5" start_j="166.60000000000002" goal_i="71" goal_j="165.70000000000002" duration="9.5425363504678273"/>
                <section number="14" start_i="71" start_j="165.70000000000002" goal_i="61.700000000000003" goal_j="166.20000000000002" duration="9.3134311615000342"/>
                <section number="15" start_i="61.700000000000003" start_j="166.20000000000002" goal_i="54.5" goal_j="169.30000000000001" duration="7.8390050389064072"/>
                <section number="16" start_i="54.5" start_j="169.30000000000001" goal_i="42.300000000000004" goal_j="173" duration="12.748725426488704"/>
                <section number="17" start_i="42.300000000000004" start_j="173" goal_i="23.800000000000001" goal_j="182.5" duration="20.796634343085429"/>
                <section number="18" start_i="23.800000000000001" start_j="182.5" goal_i="13.100000000000001" goal_j="182.90000000000001" duration="10.707474025184467"/>
            </path>
        </agent>
        <agent number="10">
            <path duration="277.77420942657477">
                <section number="0" start_i="142" start_j="219.40000000000001" goal_i="134.5" goal_j="219.10000000000002" duration="7.5059976019180814"/>
                <section number="1" start_i="134.5" start_j="219.10000000000002" goal_i="116.5" goal_j="217.40000000000001" duration="18.080099557248019"/>
                <section number="2" start_i="116.5" start_j="217.40000000000001" goal_i="101.7" goal_j="212.10000000000002" duration="15.720368952413288"/>
                <section number="3" start_i="101.7" start_j="212.10000000000002" goal_i="96.200000000000003" goal_j="205.5" duration="8.5912746434973357"/>
                <section number="4" start_i="96.200000000000003" start_j="205.5" goal_i="96.600000000000009" goal_j="181.10000000000002" duration="24.403278468271409"/>
                <section number="5" start_i="96.600000000000009" start_j="181.10000000000002" goal_i="96.5" goal_j="173.30000000000001" duration="7.8006409993025727"/>
                <section number="6" start_i="96.5" start_j="173.30000000000001" goal_i="108.2" goal_j="172.70000000000002" duration="11.715374513859985"/>
                <section number="7" start_i="108.2" start_j="172.70000000000002" goal_i="149.30000000000001" goal_j="159.10000000000002" duration="43.291685113887638"/>
                <section number="8" start_i="149.30000000000001" start_j="159.10000000000002" goal_i="154.30000000000001" goal_j="140.5" duration="19.260321908005608"/>
                <section number="9" start_i="154.30000000000001" start_j="140.5" goal_i="160.60000000000002" goal_j="136.20000000000002" duration="7.6275815302099375"/>
                <section number="10" start_i="160.60000000000002" start_j="136.20000000000002" goal_i="161.70000000000002" goal_j="128.30000000000001" duration="7.9762146410437254"/>
                <section number="11" start_i="161.70000000000002" start_j="128.30000000000001" goal_i="156.5" goal_j="118.10000000000001" duration="11.44901742508938"/>
                <section number="12" start_i="156.5" start_j="118.10000000000001" goal_i="142.59999999999999" goal_j="106.10000000000001" duration="18.363278574372288"/>
                <section number="13" start_i="142.59999999999999" start_j="106.10000000000001" goal_i="129.70000000000002" goal_j="102.7" duration="13.340539719216736"/>
                <section number="14" start_i="129.70000000000002" start_j="102.7" goal_i="120" goal_j="97.100000000000009" duration="11.200446419674535"/>
                <section number="15" start_i="120" start_j="97.100000000000009" goal_i="104.90000000000001" goal_j="93.900000000000006" duration="15.435349040433124"/>
                <section number="16" start_i="104.90000000000001" start_j="93.900000000000006" goal_i="84.5" goal_j="93.5" duration="20.403921191770991"/>
                <section number="17" start_i="84.5" start_j="93.5" goal_i="79.200000000000003" goal_j="82.900000000000006" duration="11.8511602807489"/>
                <section number="18" start_i="79.200000000000003" start_j="82.900000000000006" goal_i="77.600000000000009" goal_j="79.5" duration="3.7576588456112177"/>
            </path>
        </agent>
        <agent number="11">
            <path duration="175.13003705005298">
                <section number="0" start_i="168" start_j="26.900000000000002" goal_i="176.60000000000002" goal_j="35.899999999999999" duration="12.448293055676361"/>
                <section number="1" start_i="176.60000000000002" start_j="35.899999999999999" goal_i="182.60000000000002" goal_j="56.100000000000001" duration="21.072256642324767"/>
                <section number="2" start_i="182.60000000000002" start_j="56.100000000000001" goal_i="181.60000000000002" goal_j="78.5" duration="22.422310318073826"/>
                <section number="3" start_i="181.60000000000002" start_j="78.5" goal_i="179.20000000000002" goal_j="93.800000000000011" duration="15.487091398968381"/>
                <section number="4" start_i="179.20000000000002" start_j="93.800000000000011" goal_i="177.60000000000002" goal_j="102" duration="8.3546394296821518"/>
                <section number="5" start_i="177.60000000000002" start_j="102" goal_i="175.90000000000001" goal_j="122.5" duration="20.570367036103178"/>
                <section number="6" start_i="175.90000000000001" start_j="122.5" goal_i="185.30000000000001" goal_j="147" duration="26.241379536906976"/>
                <section number="7" start_i="185.30000000000001" start_j="147" goal_i="195.10000000000002" goal_j="169.20000000000002" duration="24.266849816158697"/>
                <section number="8" start_i="195.10000000000002" start_j="169.20000000000002" goal_i="204.90000000000001" goal_j="191.40000000000001" duration="24.26684981615864"/>
            </path>
        </agent>
        <agent number="12">
            <path duration="314.89144621719004">
                <section number="0" start_i="150.90000000000001" start_j="221.30000000000001" goal_i="134.5" goal_j="219.10000000000002" duration="16.546903033498449"/>
                <section number="1" start_i="134.5" start_j="219.10000000000002" goal_i="116.5" goal_j="217.40000000000001" duration="18.080099557248023"/>
                <section number="2" start_i="116.5" start_j="217.40000000000001" goal_i="101.7" goal_j="212.10000000000002" duration="15.720368952413288"/>
                <section number="3" start_i="101.7" start_j="212.10000000000002" goal_i="96.200000000000003" goal_j="205.5" duration="8.5912746434973357"/>
                <section number="4" start_i="96.200000000000003" start_j="205.5" goal_i="96.600000000000009" goal_j="181.10000000000002" duration="24.403278468271409"/>
                <section number="5" start_i="96.600000000000009" start_j="181.10000000000002" goal_i="96.5" goal_j="173.30000000000001" duration="7.8006409993025727"/>
                <section number="6" start_i="96.5" start_j="173.30000000000001" goal_i="109.60000000000001" goal_j="168.10000000000002" duration="14.094325099131211"/>
                <section number="7" start_i="109.60000000000001" start_j="168.10000000000002" goal_i="120.30000000000001" goal_j="163.10000000000002" duration="11.810588469674158"/>
                <section number="8" start_i="120.30000000000001" start_j="163.10000000000002" goal_i="128.40000000000001" goal_j="161.5" duration="8.2565125809872058"/>
                <section number="9" start_i="128.40000000000001" start_j="161.5" goal_i="135.59999999999999" goal_j="161.70000000000002" duration="7.2027772421476328"/>
                <section number="10" start_i="135.59999999999999" start_j="161.70000000000002" goal_i="146.5" goal_j="156.20000000000002" duration="12.209013064126026"/>
                <section number="11" start_i="146.5" start_j="156.20000000000002" goal_i="154.30000000000001" goal_j="140.5" duration="17.530829986056006"/>
                <section number="12" start_i="154.30000000000001" start_j="140.5" goal_i="160.60000000000002" goal_j="136.20000000000002" duration="7.6275815302099659"/>
                <section number="13" start_i="160.60000000000002" start_j="136.20000000000002" goal_i="161.70000000000002" goal_j="128.30000000000001" duration="7.9762146410437254"/>
                <section number="14" start_i="161.70000000000002" start_j="128.30000000000001" goal_i="156.5" goal_j="118.10000000000001" duration="11.44901742508938"/>
                <section number="15" start_i="156.5" start_j="118.10000000000001" goal_i="142.59999999999999" goal_j="106.10000000000001" duration="18.363278574372288"/>
                <section number="16" start_i="142.59999999999999" start_j="106.10000000000001" goal_i="129.70000000000002" goal_j="102.7" duration="13.340539719216736"/>
                <section number="17" start_i="129.70000000000002" start_j="102.7" goal_i="120" goal_j="97.100000000000009" duration="11.200446419674535"/>
                <section number="18" start_i="120" start_j="97.100000000000009" goal_i="104.90000000000001" goal_j="93.900000000000006" duration="15.435349040433124"/>
                <section number="19" start_i="104.90000000000001" start_j="93.900000000000006" goal_i="84.5" goal_j="93.5" duration="20.403921191770991"/>
                <section number="20" start_i="84.5" start_j="93.5" goal_i="75.900000000000006" goal_j="82.200000000000003" duration="14.20035210831054"/>
                <section number="21" start_i="75.900000000000006" start_j="82.200000000000003" goal_i="68.100000000000009" goal_j="75" duration="10.615083607772476"/>
                <section number="22" start_i="68.100000000000009" start_j="75" goal_i="60.700000000000003" goal_j="69.5" duration="9.2200867674876008"/>
                <section number="23" start_i="60.700000000000003" start_j="69.5" goal_i="53.200000000000003" goal_j="65.200000000000003" duration="8.6452298986204141"/>
                <section number="24" start_i="53.200000000000003" start_j="65.200000000000003" goal_i="49.600000000000001" goal_j="63.100000000000001" duration="4.1677331968349449"/>
            </path>
        </agent>
        <agent number="13">
            <path duration="98.895024640475498">
                <section number="0" start_i="135" start_j="96.600000000000009" goal_i="148.09999999999999" goal_j="95.400000000000006" duration="13.154847015454031"/>
                <section number="1" start_i="148.09999999999999" start_j="95.400000000000006" goal_i="156.30000000000001" goal_j="90.800000000000011" duration="9.4021274188345387"/>
                <section number="2" start_i="156.30000000000001" start_j="90.800000000000011" goal_i="163.70000000000002" goal_j="83.100000000000009" duration="10.679419459877025"/>
                <section number="3" start_i="163.70000000000002" start_j="83.100000000000009" goal_i="171.30000000000001" goal_j="74.100000000000009" duration="11.779643458101773"/>
                <section number="4" start_i="171.30000000000001" start_j="74.100000000000009" goal_i="179.10000000000002" goal_j="53.5" duration="22.027255843613396"/>
                <section number="5" start_i="179.10000000000002" start_j="53.5" goal_i="181.40000000000001" goal_j="48.300000000000004" duration="5.6859475903317929"/>
                <section number="6" start_i="181.40000000000001" start_j="48.300000000000004" goal_i="176.40000000000001" goal_j="39.400000000000006" duration="10.208329931972216"/>
                <section number="7" start_i="176.40000000000001" start_j="39.400000000000006" goal_i="176.90000000000001" goal_j="38.600000000000001" duration="0.94339811320566014"/>
                <section number="8" start_i="176.90000000000001" start_j="38.600000000000001" goal_i="171.90000000000001" goal_j="28.900000000000002" duration="10.91283647820309"/>
                <section number="9" start_i="171.90000000000001" start_j="28.900000000000002" goal_i="169" goal_j="26" duration="4.1012193308819747"/>
            </path>
        </agent>
    </log>
</root>
