<?xml version="1.0" ?>
<root>
    <agent start_id="724" goal_id="115"/>
    <agent start_id="303" goal_id="384"/>
    <agent start_id="302" goal_id="818"/>
    <agent start_id="579" goal_id="51"/>
    <agent start_id="784" goal_id="362"/>
    <agent start_id="369" goal_id="251"/>
    <agent start_id="21" goal_id="830"/>
    <agent start_id="611" goal_id="204"/>
    <agent start_id="668" goal_id="765"/>
    <agent start_id="412" goal_id="548"/>
    <agent start_id="250" goal_id="438"/>
    <agent start_id="688" goal_id="455"/>
    <agent start_id="230" goal_id="248"/>
    <agent start_id="792" goal_id="697"/>
    <agent start_id="660" goal_id="17"/>
    <agent start_id="458" goal_id="328"/>
    <agent start_id="111" goal_id="666"/>
    <agent start_id="178" goal_id="317"/>
    <agent start_id="294" goal_id="410"/>
    <agent start_id="764" goal_id="426"/>
    <agent start_id="225" goal_id="319"/>
    <agent start_id="726" goal_id="643"/>
    <agent start_id="652" goal_id="117"/>
    <agent start_id="186" goal_id="408"/>
    <agent start_id="542" goal_id="637"/>
    <agent start_id="264" goal_id="776"/>
    <agent start_id="873" goal_id="740"/>
    <agent start_id="559" goal_id="727"/>
    <agent start_id="67" goal_id="285"/>
    <agent start_id="562" goal_id="538"/>
    <agent start_id="205" goal_id="170"/>
    <agent start_id="71" goal_id="602"/>
    <agent start_id="751" goal_id="801"/>
    <agent start_id="35" goal_id="628"/>
    <agent start_id="136" goal_id="642"/>
    <agent start_id="859" goal_id="288"/>
    <agent start_id="679" goal_id="597"/>
    <agent start_id="825" goal_id="543"/>
    <agent start_id="457" goal_id="534"/>
    <agent start_id="286" goal_id="211"/>
    <agent start_id="761" goal_id="255"/>
    <agent start_id="540" goal_id="119"/>
    <agent start_id="802" goal_id="286"/>
    <agent start_id="581" goal_id="103"/>
    <agent start_id="773" goal_id="777"/>
    <agent start_id="574" goal_id="520"/>
    <agent start_id="690" goal_id="55"/>
    <agent start_id="352" goal_id="696"/>
    <agent start_id="196" goal_id="760"/>
    <agent start_id="731" goal_id="110"/>
    <agent start_id="853" goal_id="347"/>
    <agent start_id="749" goal_id="717"/>
    <agent start_id="662" goal_id="325"/>
    <agent start_id="516" goal_id="111"/>
    <agent start_id="388" goal_id="453"/>
    <agent start_id="538" goal_id="323"/>
    <agent start_id="707" goal_id="82"/>
    <agent start_id="632" goal_id="577"/>
    <agent start_id="41" goal_id="429"/>
    <agent start_id="77" goal_id="482"/>
    <agent start_id="479" goal_id="134"/>
    <agent start_id="206" goal_id="540"/>
    <agent start_id="821" goal_id="174"/>
    <agent start_id="2" goal_id="834"/>
    <agent start_id="730" goal_id="284"/>
    <agent start_id="209" goal_id="78"/>
    <agent start_id="706" goal_id="1"/>
    <agent start_id="495" goal_id="650"/>
    <agent start_id="108" goal_id="146"/>
    <agent start_id="32" goal_id="171"/>
    <agent start_id="710" goal_id="283"/>
    <agent start_id="465" goal_id="28"/>
    <agent start_id="114" goal_id="784"/>
    <agent start_id="501" goal_id="70"/>
    <agent start_id="49" goal_id="303"/>
    <agent start_id="42" goal_id="179"/>
    <agent start_id="864" goal_id="838"/>
    <agent start_id="669" goal_id="215"/>
    <agent start_id="467" goal_id="2"/>
    <agent start_id="260" goal_id="560"/>
    <agent start_id="793" goal_id="567"/>
    <log>
        <summary time="180.009135155" flowtime="2061.8978068433139" makespan="315.42382985539194"/>
        <agent number="0">
            <path duration="302.2441955425241">
                <section number="0" start_i="128.80000000000001" start_j="214.10000000000002" goal_i="116.5" goal_j="217.40000000000001" duration="12.734991166074682"/>
                <section number="1" start_i="116.5" start_j="217.40000000000001" goal_i="101.7" goal_j="212.10000000000002" duration="15.720368952413292"/>
                <section number="2" start_i="101.7" start_j="212.10000000000002" goal_i="96.200000000000003" goal_j="205.5" duration="8.5912746434973357"/>
                <section number="3" start_i="96.200000000000003" start_j="205.5" goal_i="96.600000000000009" goal_j="181.10000000000002" duration="24.403278468271402"/>
                <section number="4" start_i="96.600000000000009" start_j="181.10000000000002" goal_i="96.5" goal_j="173.30000000000001" duration="7.8006409993025727"/>
                <section number="5" start_i="96.5" start_j="173.30000000000001" goal_i="109.60000000000001" goal_j="168.10000000000002" duration="14.094325099131211"/>
                <section number="6" start_i="109.60000000000001" start_j="168.10000000000002" goal_i="120.30000000000001" goal_j="163.10000000000002" duration="11.810588469674158"/>
                <section number="7" start_i="120.30000000000001" start_j="163.10000000000002" goal_i="128.40000000000001" goal_j="161.5" duration="8.2565125809872058"/>
                <section number="8" start_i="128.40000000000001" start_j="161.5" goal_i="135.59999999999999" goal_j="161.70000000000002" duration="7.2027772421476328"/>
                <section number="9" start_i="135.59999999999999" start_j="161.70000000000002" goal_i="141.5" goal_j="163.60000000000002" duration="6.1983868869246947"/>
                <section number="10" start_i="141.5" start_j="163.60000000000002" goal_i="160.10000000000002" goal_j="150.09999999999999" duration="22.982819670353791"/>
                <section number="11" start_i="160.10000000000002" start_j="150.09999999999999" goal_i="164.5" goal_j="141.40000000000001" duration="9.7493589532850535"/>
                <section number="12" start_i="164.5" start_j="141.40000000000001" goal_i="168.5" goal_j="130.5" duration="11.610770861575048"/>
                <section number="13" start_i="168.5" start_j="130.5" goal_i="172.60000000000002" goal_j="116.2" duration="14.876155417311281"/>
                <section number="14" start_i="172.60000000000002" start_j="116.2" goal_i="176.30000000000001" goal_j="106.40000000000001" duration="10.475208828467316"/>
                <section number="15" start_i="176.30000000000001" start_j="106.40000000000001" goal_i="181.60000000000002" goal_j="98.200000000000003" duration="9.7637083119069246"/>
                <section number="16" start_i="181.60000000000002" start_j="98.200000000000003" goal_i="186.30000000000001" goal_j="91.300000000000011" duration="8.3486525858967013"/>
                <section number="17" start_i="186.30000000000001" start_j="91.300000000000011" goal_i="191.80000000000001" goal_j="86.300000000000011" duration="7.4330343736592397"/>
                <section number="18" start_i="191.80000000000001" start_j="86.300000000000011" goal_i="199.60000000000002" goal_j="83.100000000000009" duration="8.4308955633431992"/>
                <section number="19" start_i="199.60000000000002" start_j="83.100000000000009" goal_i="216.20000000000002" goal_j="72.200000000000003" duration="19.858751219550527"/>
                <section number="20" start_i="216.20000000000002" start_j="72.200000000000003" goal_i="225.10000000000002" goal_j="70.700000000000003" duration="9.0255193756370602"/>
                <section number="21" start_i="225.10000000000002" start_j="70.700000000000003" goal_i="233.90000000000001" goal_j="63" duration="11.693160394008089"/>
                <section number="22" start_i="233.90000000000001" start_j="63" goal_i="235.10000000000002" goal_j="57.700000000000003" duration="5.4341512676774073"/>
                <section number="23" start_i="235.10000000000002" start_j="57.700000000000003" goal_i="238.80000000000001" goal_j="49.700000000000003" duration="8.8141930997680902"/>
                <section number="24" start_i="238.80000000000001" start_j="49.700000000000003" goal_i="243.20000000000002" goal_j="33.700000000000003" duration="16.593974810153213"/>
                <section number="25" start_i="243.20000000000002" start_j="33.700000000000003" goal_i="246.5" goal_j="23.900000000000002" duration="10.340696301506966"/>
            </path>
        </agent>
        <agent number="1">
            <path duration="90.457187553896802">
                <section number="0" start_i="229.10000000000002" start_j="196.10000000000002" goal_i="225.90000000000001" goal_j="192.90000000000001" duration="4.5254833995939281"/>
                <section number="1" start_i="225.90000000000001" start_j="192.90000000000001" goal_i="216.30000000000001" goal_j="186.10000000000002" duration="11.764352935882179"/>
                <section number="2" start_i="216.30000000000001" start_j="186.10000000000002" goal_i="209.20000000000002" goal_j="181.80000000000001" duration="8.3006023877788557"/>
                <section number="3" start_i="209.20000000000002" start_j="181.80000000000001" goal_i="200.40000000000001" goal_j="179.30000000000001" duration="9.1482238713315382"/>
                <section number="4" start_i="200.40000000000001" start_j="179.30000000000001" goal_i="192.80000000000001" goal_j="176.70000000000002" duration="8.0324342512092741"/>
                <section number="5" start_i="192.80000000000001" start_j="176.70000000000002" goal_i="180.90000000000001" goal_j="175.10000000000002" duration="12.007081243999316"/>
                <section number="6" start_i="180.90000000000001" start_j="175.10000000000002" goal_i="156.10000000000002" goal_j="168.90000000000001" duration="25.563254878829483"/>
                <section number="7" start_i="156.10000000000002" start_j="168.90000000000001" goal_i="145.09999999999999" goal_j="167.30000000000001" duration="11.115754585272228"/>
            </path>
        </agent>
        <agent number="2">
            <path duration="83.876218990362247">
                <section number="0" start_i="47.400000000000006" start_j="166.90000000000001" goal_i="61.700000000000003" goal_j="166.20000000000002" duration="14.317122615944864"/>
                <section number="1" start_i="61.700000000000003" start_j="166.20000000000002" goal_i="71" goal_j="165.70000000000002" duration="9.3134311615000378"/>
                <section number="2" start_i="71" start_j="165.70000000000002" goal_i="80.5" goal_j="166.60000000000002" duration="9.5425363504678344"/>
                <section number="3" start_i="80.5" start_j="166.60000000000002" goal_i="89.5" goal_j="170" duration="9.6208107766445465"/>
                <section number="4" start_i="89.5" start_j="170" goal_i="96.5" goal_j="173.30000000000001" duration="7.738862965578349"/>
                <section number="5" start_i="96.5" start_j="173.30000000000001" goal_i="108.7" goal_j="174.40000000000001" duration="12.2494897852931"/>
                <section number="6" start_i="108.7" start_j="174.40000000000001" goal_i="125.2" goal_j="174.80000000000001" duration="16.504847772699989"/>
                <section number="7" start_i="125.2" start_j="174.80000000000001" goal_i="129.70000000000002" goal_j="175.70000000000002" duration="4.5891175622335254"/>
            </path>
        </agent>
        <agent number="3">
            <path duration="142.3143633987323">
                <section number="0" start_i="186.5" start_j="166.40000000000001" goal_i="186.80000000000001" goal_j="156.20000000000002" duration="10.204410811016958"/>
                <section number="1" start_i="186.80000000000001" start_j="156.20000000000002" goal_i="185.30000000000001" goal_j="147" duration="9.3214805690941756"/>
                <section number="2" start_i="185.30000000000001" start_j="147" goal_i="175.90000000000001" goal_j="122.5" duration="26.241379536906976"/>
                <section number="3" start_i="175.90000000000001" start_j="122.5" goal_i="173.70000000000002" goal_j="98.400000000000006" duration="24.200206610688255"/>
                <section number="4" start_i="173.70000000000002" start_j="98.400000000000006" goal_i="171.30000000000001" goal_j="74.100000000000009" duration="24.418230894149559"/>
                <section number="5" start_i="171.30000000000001" start_j="74.100000000000009" goal_i="166.60000000000002" goal_j="59.900000000000006" duration="14.957606760441323"/>
                <section number="6" start_i="166.60000000000002" start_j="59.900000000000006" goal_i="160.30000000000001" goal_j="51.800000000000004" duration="10.261578825892244"/>
                <section number="7" start_i="160.30000000000001" start_j="51.800000000000004" goal_i="138.90000000000001" goal_j="44.200000000000003" duration="22.709469390542807"/>
            </path>
        </agent>
        <agent number="4">
            <path duration="98.413249631448039">
                <section number="0" start_i="222.20000000000002" start_j="222.60000000000002" goal_i="218.60000000000002" goal_j="207.10000000000002" duration="15.912573644762809"/>
                <section number="1" start_i="218.60000000000002" start_j="207.10000000000002" goal_i="211.90000000000001" goal_j="200.30000000000001" duration="9.5462034338264772"/>
                <section number="2" start_i="211.90000000000001" start_j="200.30000000000001" goal_i="204.90000000000001" goal_j="191.40000000000001" duration="11.322985472038731"/>
                <section number="3" start_i="204.90000000000001" start_j="191.40000000000001" goal_i="192.80000000000001" goal_j="176.70000000000002" duration="19.039432764659757"/>
                <section number="4" start_i="192.80000000000001" start_j="176.70000000000002" goal_i="174" goal_j="168.90000000000001" duration="20.353869410998989"/>
                <section number="5" start_i="174" start_j="168.90000000000001" goal_i="159.10000000000002" goal_j="162" duration="16.420109622045743"/>
                <section number="6" start_i="159.10000000000002" start_j="162" goal_i="156.70000000000002" goal_j="156.70000000000002" duration="5.8180752831155331"/>
            </path>
        </agent>
        <agent number="5">
            <path duration="136.73560988472553">
                <section number="0" start_i="94.700000000000003" start_j="151.80000000000001" goal_i="104" goal_j="157.40000000000001" duration="10.855873986004068"/>
                <section number="1" start_i="104" start_j="157.40000000000001" goal_i="113.30000000000001" goal_j="158.70000000000002" duration="9.3904206508547947"/>
                <section number="2" start_i="113.30000000000001" start_j="158.70000000000002" goal_i="127.90000000000001" goal_j="159.40000000000001" duration="14.616771189288002"/>
                <section number="3" start_i="127.90000000000001" start_j="159.40000000000001" goal_i="146.5" goal_j="156.20000000000002" duration="18.873261509341717"/>
                <section number="4" start_i="146.5" start_j="156.20000000000002" goal_i="154.30000000000001" goal_j="140.5" duration="17.53082998605602"/>
                <section number="5" start_i="154.30000000000001" start_j="140.5" goal_i="160.60000000000002" goal_j="136.20000000000002" duration="7.6275815302099517"/>
                <section number="6" start_i="160.60000000000002" start_j="136.20000000000002" goal_i="161.70000000000002" goal_j="128.30000000000001" duration="7.9762146410437111"/>
                <section number="7" start_i="161.70000000000002" start_j="128.30000000000001" goal_i="159.80000000000001" goal_j="116.2" duration="12.248265183282086"/>
                <section number="8" start_i="159.80000000000001" start_j="116.2" goal_i="160.20000000000002" goal_j="109.5" duration="6.7119296778199384"/>
                <section number="9" start_i="160.20000000000002" start_j="109.5" goal_i="163.5" goal_j="95.700000000000003" duration="14.18908030846255"/>
                <section number="10" start_i="163.5" start_j="95.700000000000003" goal_i="163.20000000000002" goal_j="86.700000000000003" duration="9.0049986118821863"/>
                <section number="11" start_i="163.20000000000002" start_j="86.700000000000003" goal_i="162.80000000000001" goal_j="79" duration="7.710382610480508"/>
            </path>
        </agent>
        <agent number="6">
            <path duration="41.878880912623544">
                <section number="0" start_i="235.80000000000001" start_j="200.80000000000001" goal_i="225.90000000000001" goal_j="192.90000000000001" duration="12.665701717630974"/>
                <section number="1" start_i="225.90000000000001" start_j="192.90000000000001" goal_i="216.30000000000001" goal_j="186.10000000000002" duration="11.764352935882179"/>
                <section number="2" start_i="216.30000000000001" start_j="186.10000000000002" goal_i="209.20000000000002" goal_j="181.80000000000001" duration="8.3006023877788522"/>
                <section number="3" start_i="209.20000000000002" start_j="181.80000000000001" goal_i="200.40000000000001" goal_j="179.30000000000001" duration="9.1482238713315382"/>
            </path>
        </agent>
        <agent number="7">
            <path duration="315.42382985539194">
                <section number="0" start_i="68.799999999999997" start_j="46.100000000000001" goal_i="68" goal_j="55" duration="8.9358827208060418"/>
                <section number="1" start_i="68" start_j="55" goal_i="71.100000000000009" goal_j="69.299999999999997" duration="14.632156368765337"/>
                <section number="2" start_i="71.100000000000009" start_j="69.299999999999997" goal_i="72.799999999999997" goal_j="76.200000000000003" duration="7.106335201775952"/>
                <section number="3" start_i="72.799999999999997" start_j="76.200000000000003" goal_i="75.900000000000006" goal_j="82.200000000000003" duration="6.7535176019612244"/>
                <section number="4" start_i="75.900000000000006" start_j="82.200000000000003" goal_i="84.5" goal_j="93.5" duration="14.200352108310547"/>
                <section number="5" start_i="84.5" start_j="93.5" goal_i="104.90000000000001" goal_j="93.900000000000006" duration="20.403921191770969"/>
                <section number="6" start_i="104.90000000000001" start_j="93.900000000000006" goal_i="120" goal_j="97.100000000000009" duration="15.435349040433124"/>
                <section number="7" start_i="120" start_j="97.100000000000009" goal_i="129.70000000000002" goal_j="102.7" duration="11.200446419674549"/>
                <section number="8" start_i="129.70000000000002" start_j="102.7" goal_i="142.59999999999999" goal_j="106.10000000000001" duration="13.340539719216736"/>
                <section number="9" start_i="142.59999999999999" start_j="106.10000000000001" goal_i="156.5" goal_j="118.10000000000001" duration="18.363278574372288"/>
                <section number="10" start_i="156.5" start_j="118.10000000000001" goal_i="161.70000000000002" goal_j="128.30000000000001" duration="11.44901742508938"/>
                <section number="11" start_i="161.70000000000002" start_j="128.30000000000001" goal_i="160.60000000000002" goal_j="136.20000000000002" duration="7.9762146410437254"/>
                <section number="12" start_i="160.60000000000002" start_j="136.20000000000002" goal_i="154.30000000000001" goal_j="140.5" duration="7.6275815302099375"/>
                <section number="13" start_i="154.30000000000001" start_j="140.5" goal_i="146.5" goal_j="156.20000000000002" duration="17.530829986056006"/>
                <section number="14" start_i="146.5" start_j="156.20000000000002" goal_i="116.80000000000001" goal_j="159.70000000000002" duration="29.905517885500643"/>
                <section number="15" start_i="116.80000000000001" start_j="159.70000000000002" goal_i="109.5" goal_j="164" duration="8.4723078319900651"/>
                <section number="16" start_i="109.5" start_j="164" goal_i="96.5" goal_j="173.30000000000001" duration="15.984054554461466"/>
                <section number="17" start_i="96.5" start_j="173.30000000000001" goal_i="96.600000000000009" goal_j="181.10000000000002" duration="7.8006409993025727"/>
                <section number="18" start_i="96.600000000000009" start_j="181.10000000000002" goal_i="96.200000000000003" goal_j="205.5" duration="24.403278468271395"/>
                <section number="19" start_i="96.200000000000003" start_j="205.5" goal_i="101.7" goal_j="212.10000000000002" duration="8.5912746434973428"/>
                <section number="20" start_i="101.7" start_j="212.10000000000002" goal_i="116.5" goal_j="217.40000000000001" duration="15.72036895241331"/>
                <section number="21" start_i="116.5" start_j="217.40000000000001" goal_i="134.5" goal_j="219.10000000000002" duration="18.080099557247991"/>
                <section number="22" start_i="134.5" start_j="219.10000000000002" goal_i="146" goal_j="219.60000000000002" duration="11.510864433221343"/>
            </path>
        </agent>
        <agent number="8">
            <path duration="57.631660244087143">
                <section number="0" start_i="162.10000000000002" start_j="28.800000000000001" goal_i="162.30000000000001" goal_j="31.100000000000001" duration="2.3086792761230388"/>
                <section number="1" start_i="162.30000000000001" start_j="31.100000000000001" goal_i="170.90000000000001" goal_j="37" duration="10.429285689825544"/>
                <section number="2" start_i="170.90000000000001" start_j="37" goal_i="174.90000000000001" goal_j="40.700000000000003" duration="5.4488530903301129"/>
                <section number="3" start_i="174.90000000000001" start_j="40.700000000000003" goal_i="183.70000000000002" goal_j="50.300000000000004" duration="13.023056476879773"/>
                <section number="4" start_i="183.70000000000002" start_j="50.300000000000004" goal_i="191" goal_j="58.900000000000006" duration="11.280514172678465"/>
                <section number="5" start_i="191" start_j="58.900000000000006" goal_i="196.70000000000002" goal_j="64.600000000000009" duration="8.0610173055266543"/>
                <section number="6" start_i="196.70000000000002" start_j="64.600000000000009" goal_i="202.40000000000001" goal_j="68.799999999999997" duration="7.0802542327235543"/>
            </path>
        </agent>
        <agent number="9">
            <path duration="72.053382469332476">
                <section number="0" start_i="233.30000000000001" start_j="119.7" goal_i="225.80000000000001" goal_j="106.30000000000001" duration="15.356106277308704"/>
                <section number="1" start_i="225.80000000000001" start_j="106.30000000000001" goal_i="223.20000000000002" goal_j="98.900000000000006" duration="7.8434686204510342"/>
                <section number="2" start_i="223.20000000000002" start_j="98.900000000000006" goal_i="219.40000000000001" goal_j="87.5" duration="12.016655108639846"/>
                <section number="3" start_i="219.40000000000001" start_j="87.5" goal_i="219.20000000000002" goal_j="81.200000000000003" duration="6.3031738037277663"/>
                <section number="4" start_i="219.20000000000002" start_j="81.200000000000003" goal_i="216.20000000000002" goal_j="72.200000000000003" duration="9.4868329805051346"/>
                <section number="5" start_i="216.20000000000002" start_j="72.200000000000003" goal_i="211.20000000000002" goal_j="61.100000000000001" duration="12.17415294794673"/>
                <section number="6" start_i="211.20000000000002" start_j="61.100000000000001" goal_i="205.5" goal_j="54.300000000000004" duration="8.8729927307532606"/>
            </path>
        </agent>
        <agent number="10">
            <path duration="266.12744708849453">
                <section number="0" start_i="242.30000000000001" start_j="45.700000000000003" goal_i="235.10000000000002" goal_j="57.700000000000003" duration="13.994284547628714"/>
                <section number="1" start_i="235.10000000000002" start_j="57.700000000000003" goal_i="233.90000000000001" goal_j="63" duration="5.4341512676774091"/>
                <section number="2" start_i="233.90000000000001" start_j="63" goal_i="225.10000000000002" goal_j="70.700000000000003" duration="11.693160394008103"/>
                <section number="3" start_i="225.10000000000002" start_j="70.700000000000003" goal_i="216.20000000000002" goal_j="72.200000000000003" duration="9.0255193756370673"/>
                <section number="4" start_i="216.20000000000002" start_j="72.200000000000003" goal_i="200.90000000000001" goal_j="82.5" duration="18.443969204051506"/>
                <section number="5" start_i="200.90000000000001" start_j="82.5" goal_i="191.80000000000001" goal_j="86.300000000000011" duration="9.8615414616580139"/>
                <section number="6" start_i="191.80000000000001" start_j="86.300000000000011" goal_i="186.30000000000001" goal_j="91.300000000000011" duration="7.4330343736592539"/>
                <section number="7" start_i="186.30000000000001" start_j="91.300000000000011" goal_i="181.60000000000002" goal_j="98.200000000000003" duration="8.3486525858967013"/>
                <section number="8" start_i="181.60000000000002" start_j="98.200000000000003" goal_i="176.30000000000001" goal_j="106.40000000000001" duration="9.7637083119069104"/>
                <section number="9" start_i="176.30000000000001" start_j="106.40000000000001" goal_i="172.60000000000002" goal_j="116.2" duration="10.475208828467331"/>
                <section number="10" start_i="172.60000000000002" start_j="116.2" goal_i="170.20000000000002" goal_j="127.7" duration="11.747765745025731"/>
                <section number="11" start_i="170.20000000000002" start_j="127.7" goal_i="160.60000000000002" goal_j="136.20000000000002" duration="12.822246293064254"/>
                <section number="12" start_i="160.60000000000002" start_j="136.20000000000002" goal_i="154.30000000000001" goal_j="140.5" duration="7.6275815302099659"/>
                <section number="13" start_i="154.30000000000001" start_j="140.5" goal_i="146.5" goal_j="156.20000000000002" duration="17.530829986056006"/>
                <section number="14" start_i="146.5" start_j="156.20000000000002" goal_i="137.40000000000001" goal_j="158.5" duration="9.38616002420585"/>
                <section number="15" start_i="137.40000000000001" start_j="158.5" goal_i="128.40000000000001" goal_j="161.5" duration="9.4868329805051417"/>
                <section number="16" start_i="128.40000000000001" start_j="161.5" goal_i="120.30000000000001" goal_j="163.10000000000002" duration="8.2565125809871915"/>
                <section number="17" start_i="120.30000000000001" start_j="163.10000000000002" goal_i="109.60000000000001" goal_j="168.10000000000002" duration="11.810588469674144"/>
                <section number="18" start_i="109.60000000000001" start_j="168.10000000000002" goal_i="96.5" goal_j="173.30000000000001" duration="14.094325099131225"/>
                <section number="19" start_i="96.5" start_j="173.30000000000001" goal_i="94.400000000000006" goal_j="181.60000000000002" duration="8.5615419172015947"/>
                <section number="20" start_i="94.400000000000006" start_j="181.60000000000002" goal_i="91.700000000000003" goal_j="190.70000000000002" duration="9.4921019800674173"/>
                <section number="21" start_i="91.700000000000003" start_j="190.70000000000002" goal_i="77.700000000000003" goal_j="226.90000000000001" duration="38.812884458643339"/>
                <section number="22" start_i="77.700000000000003" start_j="226.90000000000001" goal_i="77" goal_j="228.80000000000001" duration="2.0248456731316651"/>
            </path>
        </agent>
        <agent number="11">
            <path duration="187.03374453519874">
                <section number="0" start_i="240.30000000000001" start_j="112.5" goal_i="235.5" goal_j="101.60000000000001" duration="11.910079764636336"/>
                <section number="1" start_i="235.5" start_j="101.60000000000001" goal_i="233.10000000000002" goal_j="98.800000000000011" duration="3.6878177829171381"/>
                <section number="2" start_i="233.10000000000002" start_j="98.800000000000011" goal_i="230.90000000000001" goal_j="98.400000000000006" duration="2.2360679774998058"/>
                <section number="3" start_i="230.90000000000001" start_j="98.400000000000006" goal_i="225.10000000000002" goal_j="92.5" duration="8.273451516749212"/>
                <section number="4" start_i="225.10000000000002" start_j="92.5" goal_i="219.40000000000001" goal_j="87.5" duration="7.5822160349069563"/>
                <section number="5" start_i="219.40000000000001" start_j="87.5" goal_i="199.60000000000002" goal_j="83.200000000000003" duration="20.261539921733473"/>
                <section number="6" start_i="199.60000000000002" start_j="83.200000000000003" goal_i="191.80000000000001" goal_j="86.300000000000011" duration="8.393449827097335"/>
                <section number="7" start_i="191.80000000000001" start_j="86.300000000000011" goal_i="186.30000000000001" goal_j="91.300000000000011" duration="7.4330343736592539"/>
                <section number="8" start_i="186.30000000000001" start_j="91.300000000000011" goal_i="181.60000000000002" goal_j="98.200000000000003" duration="8.3486525858967013"/>
                <section number="9" start_i="181.60000000000002" start_j="98.200000000000003" goal_i="176.30000000000001" goal_j="106.40000000000001" duration="9.7637083119069104"/>
                <section number="10" start_i="176.30000000000001" start_j="106.40000000000001" goal_i="172.60000000000002" goal_j="116.2" duration="10.475208828467331"/>
                <section number="11" start_i="172.60000000000002" start_j="116.2" goal_i="170.20000000000002" goal_j="127.7" duration="11.747765745025731"/>
                <section number="12" start_i="170.20000000000002" start_j="127.7" goal_i="160.60000000000002" goal_j="136.20000000000002" duration="12.822246293064254"/>
                <section number="13" start_i="160.60000000000002" start_j="136.20000000000002" goal_i="154.30000000000001" goal_j="140.5" duration="7.6275815302099659"/>
                <section number="14" start_i="154.30000000000001" start_j="140.5" goal_i="146.5" goal_j="156.20000000000002" duration="17.530829986056006"/>
                <section number="15" start_i="146.5" start_j="156.20000000000002" goal_i="137.40000000000001" goal_j="158.5" duration="9.38616002420585"/>
                <section number="16" start_i="137.40000000000001" start_j="158.5" goal_i="128.40000000000001" goal_j="161.5" duration="9.4868329805051417"/>
                <section number="17" start_i="128.40000000000001" start_j="161.5" goal_i="120.30000000000001" goal_j="163.10000000000002" duration="8.2565125809871915"/>
                <section number="18" start_i="120.30000000000001" start_j="163.10000000000002" goal_i="109.60000000000001" goal_j="168.10000000000002" duration="11.810588469674144"/>
            </path>
        </agent>
        <agent number="12">
            <path duration="28.829908767221863">
                <section number="0" start_i="20" start_j="172.90000000000001" goal_i="22.700000000000003" goal_j="156.70000000000002" duration="16.423458831805185"/>
                <section number="1" start_i="22.700000000000003" start_j="156.70000000000002" goal_i="27.100000000000001" goal_j="145.09999999999999" duration="12.406449935416678"/>
            </path>
        </agent>
        <agent number="13">
            <path duration="238.87812796927454">
                <section number="0" start_i="176.40000000000001" start_j="21.700000000000003" goal_i="179.70000000000002" goal_j="33.300000000000004" duration="12.060265337047941"/>
                <section number="1" start_i="179.70000000000002" start_j="33.300000000000004" goal_i="184.90000000000001" goal_j="43" duration="11.005907504608597"/>
                <section number="2" start_i="184.90000000000001" start_j="43" goal_i="184" goal_j="47.700000000000003" duration="4.7853944456021651"/>
                <section number="3" start_i="184" start_j="47.700000000000003" goal_i="181.60000000000002" goal_j="78.5" duration="30.893364983439398"/>
                <section number="4" start_i="181.60000000000002" start_j="78.5" goal_i="179.20000000000002" goal_j="93.800000000000011" duration="15.487091398968374"/>
                <section number="5" start_i="179.20000000000002" start_j="93.800000000000011" goal_i="176.30000000000001" goal_j="106.40000000000001" duration="12.92942380773404"/>
                <section number="6" start_i="176.30000000000001" start_j="106.40000000000001" goal_i="172.60000000000002" goal_j="116.2" duration="10.475208828467331"/>
                <section number="7" start_i="172.60000000000002" start_j="116.2" goal_i="170.20000000000002" goal_j="127.7" duration="11.747765745025731"/>
                <section number="8" start_i="170.20000000000002" start_j="127.7" goal_i="160.60000000000002" goal_j="136.20000000000002" duration="12.822246293064254"/>
                <section number="9" start_i="160.60000000000002" start_j="136.20000000000002" goal_i="154.30000000000001" goal_j="140.5" duration="7.6275815302099375"/>
                <section number="10" start_i="154.30000000000001" start_j="140.5" goal_i="146.5" goal_j="156.20000000000002" duration="17.530829986056006"/>
                <section number="11" start_i="146.5" start_j="156.20000000000002" goal_i="133.59999999999999" goal_j="157.90000000000001" duration="13.011533345459327"/>
                <section number="12" start_i="133.59999999999999" start_j="157.90000000000001" goal_i="121.60000000000001" goal_j="155.80000000000001" duration="12.182364302548166"/>
                <section number="13" start_i="121.60000000000001" start_j="155.80000000000001" goal_i="110.90000000000001" goal_j="154.20000000000002" duration="10.818964830333812"/>
                <section number="14" start_i="110.90000000000001" start_j="154.20000000000002" goal_i="91.900000000000006" goal_j="143.20000000000002" duration="21.954498400100164"/>
                <section number="15" start_i="91.900000000000006" start_j="143.20000000000002" goal_i="68.400000000000006" goal_j="142.30000000000001" duration="23.517227727774383"/>
                <section number="16" start_i="68.400000000000006" start_j="142.30000000000001" goal_i="58.800000000000004" goal_j="139.40000000000001" duration="10.02845950283492"/>
            </path>
        </agent>
    </log>
</root>
