<?xml version="1.0" ?>
<root>
    <agent start_id="3381" goal_id="5860"/>
    <agent start_id="4290" goal_id="3042"/>
    <agent start_id="174" goal_id="10153"/>
    <agent start_id="6467" goal_id="8233"/>
    <agent start_id="3213" goal_id="516"/>
    <agent start_id="2536" goal_id="6577"/>
    <agent start_id="256" goal_id="10809"/>
    <agent start_id="10227" goal_id="5540"/>
    <agent start_id="6756" goal_id="1486"/>
    <agent start_id="7442" goal_id="9269"/>
    <agent start_id="9427" goal_id="4783"/>
    <agent start_id="1322" goal_id="3570"/>
    <agent start_id="9921" goal_id="5181"/>
    <agent start_id="10398" goal_id="3918"/>
    <agent start_id="10256" goal_id="8341"/>
    <agent start_id="4234" goal_id="9624"/>
    <agent start_id="1514" goal_id="7066"/>
    <agent start_id="983" goal_id="5570"/>
    <agent start_id="11221" goal_id="3078"/>
    <agent start_id="5318" goal_id="7406"/>
    <agent start_id="4369" goal_id="7755"/>
    <agent start_id="6961" goal_id="9254"/>
    <agent start_id="5944" goal_id="7970"/>
    <agent start_id="6662" goal_id="5997"/>
    <agent start_id="7372" goal_id="5779"/>
    <agent start_id="7725" goal_id="11003"/>
    <agent start_id="9" goal_id="4203"/>
    <agent start_id="3704" goal_id="740"/>
    <agent start_id="10323" goal_id="11213"/>
    <agent start_id="2329" goal_id="454"/>
    <agent start_id="2285" goal_id="1831"/>
    <agent start_id="3747" goal_id="1874"/>
    <agent start_id="10363" goal_id="2820"/>
    <agent start_id="4546" goal_id="9555"/>
    <agent start_id="5174" goal_id="2893"/>
    <agent start_id="9588" goal_id="9957"/>
    <agent start_id="1350" goal_id="10406"/>
    <agent start_id="9416" goal_id="3430"/>
    <agent start_id="7037" goal_id="7769"/>
    <agent start_id="6101" goal_id="11306"/>
    <agent start_id="7657" goal_id="10355"/>
    <agent start_id="10073" goal_id="7208"/>
    <agent start_id="322" goal_id="9142"/>
    <agent start_id="3258" goal_id="6115"/>
    <agent start_id="5191" goal_id="9398"/>
    <agent start_id="3044" goal_id="10459"/>
    <agent start_id="8194" goal_id="702"/>
    <agent start_id="6020" goal_id="6292"/>
    <agent start_id="5876" goal_id="8576"/>
    <agent start_id="10887" goal_id="4871"/>
    <agent start_id="4252" goal_id="5816"/>
    <agent start_id="2150" goal_id="3868"/>
    <agent start_id="7165" goal_id="2305"/>
    <agent start_id="10127" goal_id="1314"/>
    <agent start_id="1348" goal_id="10225"/>
    <agent start_id="1149" goal_id="2075"/>
    <agent start_id="7108" goal_id="5172"/>
    <agent start_id="9527" goal_id="9930"/>
    <agent start_id="9642" goal_id="4144"/>
    <agent start_id="747" goal_id="5475"/>
    <agent start_id="11190" goal_id="6978"/>
    <agent start_id="22" goal_id="2068"/>
    <agent start_id="4517" goal_id="1358"/>
    <agent start_id="1272" goal_id="1423"/>
    <agent start_id="7183" goal_id="1138"/>
    <agent start_id="8925" goal_id="9395"/>
    <agent start_id="1059" goal_id="6579"/>
    <agent start_id="7641" goal_id="2545"/>
    <agent start_id="1720" goal_id="9413"/>
    <agent start_id="7671" goal_id="1032"/>
    <agent start_id="8273" goal_id="4423"/>
    <agent start_id="4046" goal_id="2916"/>
    <agent start_id="7728" goal_id="7845"/>
    <agent start_id="5875" goal_id="7977"/>
    <agent start_id="156" goal_id="10785"/>
    <agent start_id="7236" goal_id="682"/>
    <agent start_id="2584" goal_id="8952"/>
    <agent start_id="8438" goal_id="6498"/>
    <agent start_id="3052" goal_id="1526"/>
    <agent start_id="8323" goal_id="2271"/>
    <agent start_id="10737" goal_id="7267"/>
    <log>
        <summary time="180.022246142" flowtime="2473.8649108541708" makespan="312.56831548736659"/>
        <agent number="0">
            <path duration="231.67154161344956">
                <section number="0" start_i="72.5" start_j="181.10000000000002" goal_i="79.100000000000009" goal_j="177.70000000000002" duration="7.4242844773082446"/>
                <section number="1" start_i="79.100000000000009" start_j="177.70000000000002" goal_i="88.400000000000006" goal_j="174.10000000000002" duration="9.9724620831567918"/>
                <section number="2" start_i="88.400000000000006" start_j="174.10000000000002" goal_i="95" goal_j="171.30000000000001" duration="7.1693793315739676"/>
                <section number="3" start_i="95" start_j="171.30000000000001" goal_i="109.2" goal_j="165.70000000000002" duration="15.264337522473745"/>
                <section number="4" start_i="109.2" start_j="165.70000000000002" goal_i="119" goal_j="161" duration="10.868762579061155"/>
                <section number="5" start_i="119" start_j="161" goal_i="129.90000000000001" goal_j="156.20000000000002" duration="11.910079764636336"/>
                <section number="6" start_i="129.90000000000001" start_j="156.20000000000002" goal_i="138.5" goal_j="152.20000000000002" duration="9.4847245611034907"/>
                <section number="7" start_i="138.5" start_j="152.20000000000002" goal_i="144.09999999999999" goal_j="150.20000000000002" duration="5.9464274989273918"/>
                <section number="8" start_i="144.09999999999999" start_j="150.20000000000002" goal_i="159.30000000000001" goal_j="137.09999999999999" duration="20.066140635408715"/>
                <section number="9" start_i="159.30000000000001" start_j="137.09999999999999" goal_i="166.20000000000002" goal_j="125.60000000000001" duration="13.411189358144185"/>
                <section number="10" start_i="166.20000000000002" start_j="125.60000000000001" goal_i="174.30000000000001" goal_j="113.90000000000001" duration="14.230249470757713"/>
                <section number="11" start_i="174.30000000000001" start_j="113.90000000000001" goal_i="182.10000000000002" goal_j="102.2" duration="14.061649974309574"/>
                <section number="12" start_i="182.10000000000002" start_j="102.2" goal_i="185.30000000000001" goal_j="96.300000000000011" duration="6.71192967781991"/>
                <section number="13" start_i="185.30000000000001" start_j="96.300000000000011" goal_i="191.80000000000001" goal_j="86.100000000000009" duration="12.095040305844378"/>
                <section number="14" start_i="191.80000000000001" start_j="86.100000000000009" goal_i="201.20000000000002" goal_j="78.5" duration="12.088010589009258"/>
                <section number="15" start_i="201.20000000000002" start_j="78.5" goal_i="224" goal_j="60.5" duration="29.048924248584484"/>
                <section number="16" start_i="224" start_j="60.5" goal_i="228.80000000000001" goal_j="56.800000000000004" duration="6.0605280298007074"/>
                <section number="17" start_i="228.80000000000001" start_j="56.800000000000004" goal_i="232.40000000000001" goal_j="54.200000000000003" duration="4.4407206622348951"/>
                <section number="18" start_i="232.40000000000001" start_j="54.200000000000003" goal_i="237.10000000000002" goal_j="47" duration="8.5982556370464067"/>
                <section number="19" start_i="237.10000000000002" start_j="47" goal_i="241.80000000000001" goal_j="39.800000000000004" duration="8.5982556370463783"/>
                <section number="20" start_i="241.80000000000001" start_j="39.800000000000004" goal_i="244.30000000000001" goal_j="36.399999999999999" duration="4.2201895692018354"/>
            </path>
        </agent>
        <agent number="1">
            <path duration="37.743302588020924">
                <section number="0" start_i="145.59999999999999" start_j="92.400000000000006" goal_i="146.5" goal_j="92.400000000000006" duration="0.90000000000000568"/>
                <section number="1" start_i="146.5" start_j="92.400000000000006" goal_i="150.30000000000001" goal_j="92.5" duration="3.8013155617496537"/>
                <section number="2" start_i="150.30000000000001" start_j="92.5" goal_i="156.20000000000002" goal_j="90.700000000000003" duration="6.1684682053164579"/>
                <section number="3" start_i="156.20000000000002" start_j="90.700000000000003" goal_i="157.40000000000001" goal_j="88.600000000000009" duration="2.4186773244895541"/>
                <section number="4" start_i="157.40000000000001" start_j="88.600000000000009" goal_i="160.30000000000001" goal_j="85.600000000000009" duration="4.1725292090050168"/>
                <section number="5" start_i="160.30000000000001" start_j="85.600000000000009" goal_i="162.80000000000001" goal_j="82.5" duration="3.9824615503479812"/>
                <section number="6" start_i="162.80000000000001" start_j="82.5" goal_i="165.60000000000002" goal_j="78" duration="5.3000000000000078"/>
                <section number="7" start_i="165.60000000000002" start_j="78" goal_i="166.70000000000002" goal_j="74.700000000000003" duration="3.4785054261852117"/>
                <section number="8" start_i="166.70000000000002" start_j="74.700000000000003" goal_i="169.60000000000002" goal_j="70.700000000000003" duration="4.940647730814252"/>
                <section number="9" start_i="169.60000000000002" start_j="70.700000000000003" goal_i="171.70000000000002" goal_j="69.200000000000003" duration="2.5806975801127834"/>
            </path>
        </agent>
        <agent number="2">
            <path duration="308.25886171283895">
                <section number="0" start_i="14.5" start_j="214.80000000000001" goal_i="15.9" goal_j="207.5" duration="7.4330343736592637"/>
                <section number="1" start_i="15.9" start_j="207.5" goal_i="17" goal_j="201.10000000000002" duration="6.4938432380216655"/>
                <section number="2" start_i="17" start_j="201.10000000000002" goal_i="17.900000000000002" goal_j="194.5" duration="6.6610809933523782"/>
                <section number="3" start_i="17.900000000000002" start_j="194.5" goal_i="18.600000000000001" goal_j="188.20000000000002" duration="6.3387695966961743"/>
                <section number="4" start_i="18.600000000000001" start_j="188.20000000000002" goal_i="19.900000000000002" goal_j="185.20000000000002" duration="3.269556544854364"/>
                <section number="5" start_i="19.900000000000002" start_j="185.20000000000002" goal_i="23.300000000000001" goal_j="182.10000000000002" duration="4.6010868281309278"/>
                <section number="6" start_i="23.300000000000001" start_j="182.10000000000002" goal_i="29.800000000000001" goal_j="180.60000000000002" duration="6.6708320320631671"/>
                <section number="7" start_i="29.800000000000001" start_j="180.60000000000002" goal_i="38.800000000000004" goal_j="177.30000000000001" duration="9.58592718520228"/>
                <section number="8" start_i="38.800000000000004" start_j="177.30000000000001" goal_i="47.300000000000004" goal_j="174.70000000000002" duration="8.8887569434651539"/>
                <section number="9" start_i="47.300000000000004" start_j="174.70000000000002" goal_i="56" goal_j="172.10000000000002" duration="9.0801982357215039"/>
                <section number="10" start_i="56" start_j="172.10000000000002" goal_i="67.5" goal_j="168.70000000000002" duration="11.992080720208648"/>
                <section number="11" start_i="67.5" start_j="168.70000000000002" goal_i="74.299999999999997" goal_j="167" duration="7.0092795635500238"/>
                <section number="12" start_i="74.299999999999997" start_j="167" goal_i="78.800000000000011" goal_j="165.70000000000002" duration="4.684015371452162"/>
                <section number="13" start_i="78.800000000000011" start_j="165.70000000000002" goal_i="83.600000000000009" goal_j="164.20000000000002" duration="5.0289163842720654"/>
                <section number="14" start_i="83.600000000000009" start_j="164.20000000000002" goal_i="90.300000000000011" goal_j="162.80000000000001" duration="6.8447059834590505"/>
                <section number="15" start_i="90.300000000000011" start_j="162.80000000000001" goal_i="95.600000000000009" goal_j="161.80000000000001" duration="5.3935146240647214"/>
                <section number="16" start_i="95.600000000000009" start_j="161.80000000000001" goal_i="101.30000000000001" goal_j="161.10000000000002" duration="5.7428216061444886"/>
                <section number="17" start_i="101.30000000000001" start_j="161.10000000000002" goal_i="107.10000000000001" goal_j="159.60000000000002" duration="5.9908263203000587"/>
                <section number="18" start_i="107.10000000000001" start_j="159.60000000000002" goal_i="110.10000000000001" goal_j="158.90000000000001" duration="3.0805843601498708"/>
                <section number="19" start_i="110.10000000000001" start_j="158.90000000000001" goal_i="143.59999999999999" goal_j="150.40000000000001" duration="34.56153931757089"/>
                <section number="20" start_i="143.59999999999999" start_j="150.40000000000001" goal_i="153.30000000000001" goal_j="142.90000000000001" duration="12.261321299109653"/>
                <section number="21" start_i="153.30000000000001" start_j="142.90000000000001" goal_i="159.30000000000001" goal_j="137.09999999999999" duration="8.3450584180100407"/>
                <section number="22" start_i="159.30000000000001" start_j="137.09999999999999" goal_i="160.80000000000001" goal_j="120" duration="17.165663401103956"/>
                <section number="23" start_i="160.80000000000001" start_j="120" goal_i="161.70000000000002" goal_j="111.80000000000001" duration="8.2492423894561284"/>
                <section number="24" start_i="161.70000000000002" start_j="111.80000000000001" goal_i="162.80000000000001" goal_j="105.30000000000001" duration="6.5924198895397979"/>
                <section number="25" start_i="162.80000000000001" start_j="105.30000000000001" goal_i="163" goal_j="97.100000000000009" duration="8.2024386617639493"/>
                <section number="26" start_i="163" start_j="97.100000000000009" goal_i="165" goal_j="85.200000000000003" duration="12.066896867049138"/>
                <section number="27" start_i="165" start_j="85.200000000000003" goal_i="165.10000000000002" goal_j="71.200000000000003" duration="14.000357138301865"/>
                <section number="28" start_i="165.10000000000002" start_j="71.200000000000003" goal_i="165.20000000000002" goal_j="65.100000000000009" duration="6.1008196170678559"/>
                <section number="29" start_i="165.20000000000002" start_j="65.100000000000009" goal_i="165.10000000000002" goal_j="59.700000000000003" duration="5.400925846556305"/>
                <section number="30" start_i="165.10000000000002" start_j="59.700000000000003" goal_i="162.40000000000001" goal_j="56.800000000000004" duration="3.9623225512318072"/>
                <section number="31" start_i="162.40000000000001" start_j="56.800000000000004" goal_i="160.70000000000002" goal_j="55.5" duration="2.1400934559032407"/>
                <section number="32" start_i="160.70000000000002" start_j="55.5" goal_i="156.60000000000002" goal_j="52.5" duration="5.0803543183521924"/>
                <section number="33" start_i="156.60000000000002" start_j="52.5" goal_i="155.70000000000002" goal_j="51.700000000000003" duration="1.2041594578792569"/>
                <section number="34" start_i="155.70000000000002" start_j="51.700000000000003" goal_i="153.90000000000001" goal_j="50.600000000000001" duration="2.1095023109729141"/>
                <section number="35" start_i="153.90000000000001" start_j="50.600000000000001" goal_i="150.30000000000001" goal_j="47.800000000000004" duration="4.5607017003965211"/>
                <section number="36" start_i="150.30000000000001" start_j="47.800000000000004" goal_i="142.90000000000001" goal_j="42.300000000000004" duration="9.2200867674876008"/>
                <section number="37" start_i="142.90000000000001" start_j="42.300000000000004" goal_i="130.5" goal_j="33.100000000000001" duration="15.440207252495043"/>
                <section number="38" start_i="130.5" start_j="33.100000000000001" goal_i="130.09999999999999" goal_j="29.5" duration="3.6221540552549527"/>
                <section number="39" start_i="130.09999999999999" start_j="29.5" goal_i="127.80000000000001" goal_j="27.300000000000001" duration="3.1827660925678742"/>
            </path>
        </agent>
        <agent number="3">
            <path duration="312.56831548736659">
                <section number="0" start_i="35" start_j="75.299999999999997" goal_i="42.600000000000001" goal_j="77.800000000000011" duration="8.0006249755878507"/>
                <section number="1" start_i="42.600000000000001" start_j="77.800000000000011" goal_i="52.800000000000004" goal_j="81.400000000000006" duration="10.816653826391967"/>
                <section number="2" start_i="52.800000000000004" start_j="81.400000000000006" goal_i="54.5" goal_j="82" duration="1.8027756377319903"/>
                <section number="3" start_i="54.5" start_j="82" goal_i="62.300000000000004" goal_j="84.200000000000003" duration="8.1043198357419293"/>
                <section number="4" start_i="62.300000000000004" start_j="84.200000000000003" goal_i="69" goal_j="86.800000000000011" duration="7.1867934435323768"/>
                <section number="5" start_i="69" start_j="86.800000000000011" goal_i="74.100000000000009" goal_j="88.700000000000003" duration="5.4424259296751174"/>
                <section number="6" start_i="74.100000000000009" start_j="88.700000000000003" goal_i="80.5" goal_j="90.800000000000011" duration="6.7357256476195602"/>
                <section number="7" start_i="80.5" start_j="90.800000000000011" goal_i="87.700000000000003" goal_j="93.300000000000011" duration="7.6216796049164941"/>
                <section number="8" start_i="87.700000000000003" start_j="93.300000000000011" goal_i="92.700000000000003" goal_j="94.600000000000009" duration="5.1662365412357971"/>
                <section number="9" start_i="92.700000000000003" start_j="94.600000000000009" goal_i="99.600000000000009" goal_j="96.600000000000009" duration="7.1840100222647223"/>
                <section number="10" start_i="99.600000000000009" start_j="96.600000000000009" goal_i="107.10000000000001" goal_j="99.900000000000006" duration="8.1939001702485967"/>
                <section number="11" start_i="107.10000000000001" start_j="99.900000000000006" goal_i="113.10000000000001" goal_j="101.90000000000001" duration="6.3245553203367564"/>
                <section number="12" start_i="113.10000000000001" start_j="101.90000000000001" goal_i="121.40000000000001" goal_j="104.5" duration="8.6977008456258034"/>
                <section number="13" start_i="121.40000000000001" start_j="104.5" goal_i="130.70000000000002" goal_j="107.60000000000001" duration="9.803060746521993"/>
                <section number="14" start_i="130.70000000000002" start_j="107.60000000000001" goal_i="138.20000000000002" goal_j="108.60000000000001" duration="7.5663729752107827"/>
                <section number="15" start_i="138.20000000000002" start_j="108.60000000000001" goal_i="143" goal_j="110.7" duration="5.2392747589718738"/>
                <section number="16" start_i="143" start_j="110.7" goal_i="148.09999999999999" goal_j="114.10000000000001" duration="6.1294371682887743"/>
                <section number="17" start_i="148.09999999999999" start_j="114.10000000000001" goal_i="150.40000000000001" goal_j="116.90000000000001" duration="3.6235341863986861"/>
                <section number="18" start_i="150.40000000000001" start_j="116.90000000000001" goal_i="154.80000000000001" goal_j="120.80000000000001" duration="5.8796258384356435"/>
                <section number="19" start_i="154.80000000000001" start_j="120.80000000000001" goal_i="155.5" goal_j="122.10000000000001" duration="1.4764823060233425"/>
                <section number="20" start_i="155.5" start_j="122.10000000000001" goal_i="157.60000000000002" goal_j="127.90000000000001" duration="6.1684682053164579"/>
                <section number="21" start_i="157.60000000000002" start_j="127.90000000000001" goal_i="159.20000000000002" goal_j="133" duration="5.3450912059570896"/>
                <section number="22" start_i="159.20000000000002" start_j="133" goal_i="159.30000000000001" goal_j="137.09999999999999" duration="4.1012193308819747"/>
                <section number="23" start_i="159.30000000000001" start_j="137.09999999999999" goal_i="153.30000000000001" goal_j="142.90000000000001" duration="8.3450584180100407"/>
                <section number="24" start_i="153.30000000000001" start_j="142.90000000000001" goal_i="143.59999999999999" goal_j="150.40000000000001" duration="12.261321299109653"/>
                <section number="25" start_i="143.59999999999999" start_j="150.40000000000001" goal_i="138" goal_j="153.60000000000002" duration="6.4498061986388393"/>
                <section number="26" start_i="138" start_j="153.60000000000002" goal_i="126.10000000000001" goal_j="161.40000000000001" duration="14.228492541376255"/>
                <section number="27" start_i="126.10000000000001" start_j="161.40000000000001" goal_i="118.30000000000001" goal_j="165.60000000000002" duration="8.8588938361400551"/>
                <section number="28" start_i="118.30000000000001" start_j="165.60000000000002" goal_i="115.60000000000001" goal_j="166.90000000000001" duration="2.9966648127543465"/>
                <section number="29" start_i="115.60000000000001" start_j="166.90000000000001" goal_i="108.40000000000001" goal_j="170.80000000000001" duration="8.1884064383737041"/>
                <section number="30" start_i="108.40000000000001" start_j="170.80000000000001" goal_i="105.90000000000001" goal_j="172.10000000000002" duration="2.8178005607210821"/>
                <section number="31" start_i="105.90000000000001" start_j="172.10000000000002" goal_i="101.5" goal_j="173.70000000000002" duration="4.6818799642878446"/>
                <section number="32" start_i="101.5" start_j="173.70000000000002" goal_i="99.800000000000011" goal_j="175.30000000000001" duration="2.334523505985743"/>
                <section number="33" start_i="99.800000000000011" start_j="175.30000000000001" goal_i="97.200000000000003" goal_j="177.60000000000002" duration="3.4713109915419693"/>
                <section number="34" start_i="97.200000000000003" start_j="177.60000000000002" goal_i="96.800000000000011" goal_j="184" duration="6.412487816752531"/>
                <section number="35" start_i="96.800000000000011" start_j="184" goal_i="97.100000000000009" goal_j="195.5" duration="11.503912377969499"/>
                <section number="36" start_i="97.100000000000009" start_j="195.5" goal_i="100.10000000000001" goal_j="209.40000000000001" duration="14.220056258679165"/>
                <section number="37" start_i="100.10000000000001" start_j="209.40000000000001" goal_i="107.5" goal_j="214.60000000000002" duration="9.0443352436760165"/>
                <section number="38" start_i="107.5" start_j="214.60000000000002" goal_i="112.5" goal_j="215.90000000000001" duration="5.1662365412357758"/>
                <section number="39" start_i="112.5" start_j="215.90000000000001" goal_i="125.90000000000001" goal_j="220.40000000000001" duration="14.135416513141763"/>
                <section number="40" start_i="125.90000000000001" start_j="220.40000000000001" goal_i="141.80000000000001" goal_j="225.40000000000001" duration="16.667633305301649"/>
                <section number="41" start_i="141.80000000000001" start_j="225.40000000000001" goal_i="147" goal_j="226.40000000000001" duration="5.2952809179494693"/>
                <section number="42" start_i="147" start_j="226.40000000000001" goal_i="152.59999999999999" goal_j="230.60000000000002" duration="7"/>
                <section number="43" start_i="152.59999999999999" start_j="230.60000000000002" goal_i="154.30000000000001" goal_j="231.40000000000001" duration="1.8788294228056088"/>
            </path>
        </agent>
        <agent number="4">
            <path duration="174.57372922077673">
                <section number="0" start_i="118.40000000000001" start_j="42.400000000000006" goal_i="123" goal_j="43.400000000000006" duration="4.707440918375922"/>
                <section number="1" start_i="123" start_j="43.400000000000006" goal_i="130.70000000000002" goal_j="45.200000000000003" duration="7.9075912893877005"/>
                <section number="2" start_i="130.70000000000002" start_j="45.200000000000003" goal_i="138.80000000000001" goal_j="47.100000000000001" duration="8.3198557679805916"/>
                <section number="3" start_i="138.80000000000001" start_j="47.100000000000001" goal_i="145" goal_j="48.400000000000006" duration="6.3348243858847333"/>
                <section number="4" start_i="145" start_j="48.400000000000006" goal_i="145.30000000000001" goal_j="48.900000000000006" duration="0.58309518948453487"/>
                <section number="5" start_i="145.30000000000001" start_j="48.900000000000006" goal_i="148.59999999999999" goal_j="48.600000000000001" duration="3.313608305156162"/>
                <section number="6" start_i="148.59999999999999" start_j="48.600000000000001" goal_i="153.90000000000001" goal_j="50.600000000000001" duration="5.6648036153074273"/>
                <section number="7" start_i="153.90000000000001" start_j="50.600000000000001" goal_i="155.70000000000002" goal_j="51.700000000000003" duration="2.109502310972907"/>
                <section number="8" start_i="155.70000000000002" start_j="51.700000000000003" goal_i="156.60000000000002" goal_j="52.5" duration="1.2041594578792285"/>
                <section number="9" start_i="156.60000000000002" start_j="52.5" goal_i="160.70000000000002" goal_j="55.5" duration="5.0803543183522137"/>
                <section number="10" start_i="160.70000000000002" start_j="55.5" goal_i="162.40000000000001" goal_j="56.800000000000004" duration="2.1400934559032621"/>
                <section number="11" start_i="162.40000000000001" start_j="56.800000000000004" goal_i="165.10000000000002" goal_j="59.700000000000003" duration="3.9623225512318001"/>
                <section number="12" start_i="165.10000000000002" start_j="59.700000000000003" goal_i="165.20000000000002" goal_j="65.100000000000009" duration="5.4009258465563192"/>
                <section number="13" start_i="165.20000000000002" start_j="65.100000000000009" goal_i="165.10000000000002" goal_j="71.200000000000003" duration="6.1008196170678488"/>
                <section number="14" start_i="165.10000000000002" start_j="71.200000000000003" goal_i="165" goal_j="85.200000000000003" duration="14.000357138301858"/>
                <section number="15" start_i="165" start_j="85.200000000000003" goal_i="163" goal_j="97.100000000000009" duration="12.066896867049138"/>
                <section number="16" start_i="163" start_j="97.100000000000009" goal_i="162.80000000000001" goal_j="105.30000000000001" duration="8.2024386617639493"/>
                <section number="17" start_i="162.80000000000001" start_j="105.30000000000001" goal_i="161.70000000000002" goal_j="111.80000000000001" duration="6.5924198895397979"/>
                <section number="18" start_i="161.70000000000002" start_j="111.80000000000001" goal_i="160.80000000000001" goal_j="120" duration="8.2492423894561284"/>
                <section number="19" start_i="160.80000000000001" start_j="120" goal_i="159.30000000000001" goal_j="137.09999999999999" duration="17.165663401103956"/>
                <section number="20" start_i="159.30000000000001" start_j="137.09999999999999" goal_i="153.30000000000001" goal_j="142.90000000000001" duration="8.3450584180100407"/>
                <section number="21" start_i="153.30000000000001" start_j="142.90000000000001" goal_i="146.80000000000001" goal_j="148.20000000000002" duration="8.3868945385047198"/>
                <section number="22" start_i="146.80000000000001" start_j="148.20000000000002" goal_i="137.09999999999999" goal_j="149.40000000000001" duration="9.7739449558507374"/>
                <section number="23" start_i="137.09999999999999" start_j="149.40000000000001" goal_i="134.5" goal_j="150.09999999999999" duration="2.6925824035672292"/>
                <section number="24" start_i="134.5" start_j="150.09999999999999" goal_i="130.80000000000001" goal_j="151.5" duration="3.9560080889704921"/>
                <section number="25" start_i="130.80000000000001" start_j="151.5" goal_i="127.2" goal_j="152.09999999999999" duration="3.649657518178941"/>
                <section number="26" start_i="127.2" start_j="152.09999999999999" goal_i="124.7" goal_j="152" duration="2.5019992006393466"/>
                <section number="27" start_i="124.7" start_j="152" goal_i="118.7" goal_j="153.40000000000001" duration="6.1611687202997416"/>
            </path>
        </agent>
        <agent number="5">
            <path duration="140.69857603669902">
                <section number="0" start_i="203.30000000000001" start_j="81.400000000000006" goal_i="195.80000000000001" goal_j="85.100000000000009" duration="8.3630138108220304"/>
                <section number="1" start_i="195.80000000000001" start_j="85.100000000000009" goal_i="188.30000000000001" goal_j="89.200000000000003" duration="8.5475142585432398"/>
                <section number="2" start_i="188.30000000000001" start_j="89.200000000000003" goal_i="183.30000000000001" goal_j="96.800000000000011" duration="9.0972523324353318"/>
                <section number="3" start_i="183.30000000000001" start_j="96.800000000000011" goal_i="176.90000000000001" goal_j="106.5" duration="11.621101496846151"/>
                <section number="4" start_i="176.90000000000001" start_j="106.5" goal_i="171.40000000000001" goal_j="116" duration="10.977249200050075"/>
                <section number="5" start_i="171.40000000000001" start_j="116" goal_i="165.10000000000002" goal_j="127.2" duration="12.85029182548007"/>
                <section number="6" start_i="165.10000000000002" start_j="127.2" goal_i="159.30000000000001" goal_j="137.09999999999999" duration="11.47388338793801"/>
                <section number="7" start_i="159.30000000000001" start_j="137.09999999999999" goal_i="153.30000000000001" goal_j="142.90000000000001" duration="8.3450584180100407"/>
                <section number="8" start_i="153.30000000000001" start_j="142.90000000000001" goal_i="143.59999999999999" goal_j="150.40000000000001" duration="12.261321299109667"/>
                <section number="9" start_i="143.59999999999999" start_j="150.40000000000001" goal_i="138" goal_j="153.60000000000002" duration="6.4498061986388393"/>
                <section number="10" start_i="138" start_j="153.60000000000002" goal_i="126.10000000000001" goal_j="161.40000000000001" duration="14.228492541376241"/>
                <section number="11" start_i="126.10000000000001" start_j="161.40000000000001" goal_i="118.30000000000001" goal_j="165.60000000000002" duration="8.8588938361400409"/>
                <section number="12" start_i="118.30000000000001" start_j="165.60000000000002" goal_i="111.30000000000001" goal_j="170.10000000000002" duration="8.3216584885466176"/>
                <section number="13" start_i="111.30000000000001" start_j="170.10000000000002" goal_i="107.80000000000001" goal_j="171.80000000000001" duration="3.8910152916687366"/>
                <section number="14" start_i="107.80000000000001" start_j="171.80000000000001" goal_i="103" goal_j="174.30000000000001" duration="5.4120236510939321"/>
            </path>
        </agent>
        <agent number="6">
            <path duration="154.39150401724402">
                <section number="0" start_i="79" start_j="134.70000000000002" goal_i="91.300000000000011" goal_j="141.59999999999999" duration="14.103191128251789"/>
                <section number="1" start_i="91.300000000000011" start_j="141.59999999999999" goal_i="100.2" goal_j="147.30000000000001" duration="10.56882207249228"/>
                <section number="2" start_i="100.2" start_j="147.30000000000001" goal_i="102.90000000000001" goal_j="149.30000000000001" duration="3.3600595232822918"/>
                <section number="3" start_i="102.90000000000001" start_j="149.30000000000001" goal_i="106.60000000000001" goal_j="151.40000000000001" duration="4.254409477236532"/>
                <section number="4" start_i="106.60000000000001" start_j="151.40000000000001" goal_i="109.60000000000001" goal_j="152.80000000000001" duration="3.3105890714493711"/>
                <section number="5" start_i="109.60000000000001" start_j="152.80000000000001" goal_i="113.80000000000001" goal_j="154" duration="4.3680659335683103"/>
                <section number="6" start_i="113.80000000000001" start_j="154" goal_i="117.10000000000001" goal_j="153.40000000000001" duration="3.3541019662496794"/>
                <section number="7" start_i="117.10000000000001" start_j="153.40000000000001" goal_i="124.7" goal_j="152" duration="7.7278716345446554"/>
                <section number="8" start_i="124.7" start_j="152" goal_i="127.2" goal_j="152.09999999999999" duration="2.5019992006393608"/>
                <section number="9" start_i="127.2" start_j="152.09999999999999" goal_i="130.80000000000001" goal_j="151.5" duration="3.649657518178941"/>
                <section number="10" start_i="130.80000000000001" start_j="151.5" goal_i="134.5" goal_j="150.09999999999999" duration="3.9560080889704849"/>
                <section number="11" start_i="134.5" start_j="150.09999999999999" goal_i="137.09999999999999" goal_j="149.40000000000001" duration="2.6925824035672434"/>
                <section number="12" start_i="137.09999999999999" start_j="149.40000000000001" goal_i="146.80000000000001" goal_j="148.20000000000002" duration="9.7739449558507516"/>
                <section number="13" start_i="146.80000000000001" start_j="148.20000000000002" goal_i="153.30000000000001" goal_j="142.90000000000001" duration="8.3868945385047056"/>
                <section number="14" start_i="153.30000000000001" start_j="142.90000000000001" goal_i="159.30000000000001" goal_j="137.09999999999999" duration="8.3450584180100265"/>
                <section number="15" start_i="159.30000000000001" start_j="137.09999999999999" goal_i="165.10000000000002" goal_j="127.2" duration="11.473883387938017"/>
                <section number="16" start_i="165.10000000000002" start_j="127.2" goal_i="171.40000000000001" goal_j="116" duration="12.85029182548007"/>
                <section number="17" start_i="171.40000000000001" start_j="116" goal_i="176.90000000000001" goal_j="106.5" duration="10.977249200050082"/>
                <section number="18" start_i="176.90000000000001" start_j="106.5" goal_i="183.30000000000001" goal_j="96.800000000000011" duration="11.621101496846165"/>
                <section number="19" start_i="183.30000000000001" start_j="96.800000000000011" goal_i="188.30000000000001" goal_j="89.200000000000003" duration="9.097252332435346"/>
                <section number="20" start_i="188.30000000000001" start_j="89.200000000000003" goal_i="191.5" goal_j="83.700000000000003" duration="6.3631753079732221"/>
                <section number="21" start_i="191.5" start_j="83.700000000000003" goal_i="192.20000000000002" goal_j="82.200000000000003" duration="1.6552945357246927"/>
            </path>
        </agent>
        <agent number="7">
            <path duration="51.154472738312606">
                <section number="0" start_i="181.80000000000001" start_j="94" goal_i="181.70000000000002" goal_j="91.100000000000009" duration="2.9017236257093728"/>
                <section number="1" start_i="181.70000000000002" start_j="91.100000000000009" goal_i="181.60000000000002" goal_j="86.600000000000009" duration="4.5011109739707598"/>
                <section number="2" start_i="181.60000000000002" start_j="86.600000000000009" goal_i="181.40000000000001" goal_j="79.400000000000006" duration="7.2027772421476461"/>
                <section number="3" start_i="181.40000000000001" start_j="79.400000000000006" goal_i="181.20000000000002" goal_j="73.5" duration="5.9033888572581805"/>
                <section number="4" start_i="181.20000000000002" start_j="73.5" goal_i="181" goal_j="67.799999999999997" duration="5.7035076926396826"/>
                <section number="5" start_i="181" start_j="67.799999999999997" goal_i="181.20000000000002" goal_j="55.600000000000001" duration="12.201639234135712"/>
                <section number="6" start_i="181.20000000000002" start_j="55.600000000000001" goal_i="180.10000000000002" goal_j="48.800000000000004" duration="6.8883960397178043"/>
                <section number="7" start_i="180.10000000000002" start_j="48.800000000000004" goal_i="180" goal_j="46.600000000000001" duration="2.2022715545545282"/>
                <section number="8" start_i="180" start_j="46.600000000000001" goal_i="177.80000000000001" goal_j="44.5" duration="3.0413812651491057"/>
                <section number="9" start_i="177.80000000000001" start_j="44.5" goal_i="177.20000000000002" goal_j="44.400000000000006" duration="0.60827625302981403"/>
            </path>
        </agent>
        <agent number="8">
            <path duration="71.127553315185523">
                <section number="0" start_i="131.70000000000002" start_j="51.5" goal_i="131.80000000000001" goal_j="51.200000000000003" duration="0.31622776601683344"/>
                <section number="1" start_i="131.80000000000001" start_j="51.200000000000003" goal_i="133.20000000000002" goal_j="50.5" duration="1.565247584249859"/>
                <section number="2" start_i="133.20000000000002" start_j="50.5" goal_i="138.80000000000001" goal_j="47.100000000000001" duration="6.5513357416636744"/>
                <section number="3" start_i="138.80000000000001" start_j="47.100000000000001" goal_i="145" goal_j="48.400000000000006" duration="6.3348243858847315"/>
                <section number="4" start_i="145" start_j="48.400000000000006" goal_i="145.30000000000001" goal_j="48.900000000000006" duration="0.58309518948453665"/>
                <section number="5" start_i="145.30000000000001" start_j="48.900000000000006" goal_i="148.59999999999999" goal_j="48.600000000000001" duration="3.3136083051561602"/>
                <section number="6" start_i="148.59999999999999" start_j="48.600000000000001" goal_i="153.90000000000001" goal_j="50.600000000000001" duration="5.6648036153074273"/>
                <section number="7" start_i="153.90000000000001" start_j="50.600000000000001" goal_i="159.20000000000002" goal_j="53" duration="5.8180752831155544"/>
                <section number="8" start_i="159.20000000000002" start_j="53" goal_i="168.30000000000001" goal_j="55.200000000000003" duration="9.3621578709184305"/>
                <section number="9" start_i="168.30000000000001" start_j="55.200000000000003" goal_i="171.90000000000001" goal_j="56.300000000000004" duration="3.7643060449437371"/>
                <section number="10" start_i="171.90000000000001" start_j="56.300000000000004" goal_i="176.40000000000001" goal_j="55.5" duration="4.5705579528105744"/>
                <section number="11" start_i="176.40000000000001" start_j="55.5" goal_i="178.5" goal_j="52.800000000000004" duration="3.420526275297405"/>
                <section number="12" start_i="178.5" start_j="52.800000000000004" goal_i="182.20000000000002" goal_j="50.600000000000001" duration="4.3046486500061931"/>
                <section number="13" start_i="182.20000000000002" start_j="50.600000000000001" goal_i="181.30000000000001" goal_j="45.100000000000001" duration="5.5731499172371102"/>
                <section number="14" start_i="181.30000000000001" start_j="45.100000000000001" goal_i="182.60000000000002" goal_j="35.200000000000003" duration="9.9849887330932958"/>
            </path>
        </agent>
        <agent number="9">
            <path duration="265.56472974691195">
                <section number="0" start_i="96.800000000000011" start_j="61.900000000000006" goal_i="94.100000000000009" goal_j="61.600000000000001" duration="2.7166155414412283"/>
                <section number="1" start_i="94.100000000000009" start_j="61.600000000000001" goal_i="91.100000000000009" goal_j="61" duration="3.0594117081556713"/>
                <section number="2" start_i="91.100000000000009" start_j="61" goal_i="86.700000000000003" goal_j="60.800000000000004" duration="4.4045431091090537"/>
                <section number="3" start_i="86.700000000000003" start_j="60.800000000000004" goal_i="85.900000000000006" goal_j="61.100000000000001" duration="0.85440037453174966"/>
                <section number="4" start_i="85.900000000000006" start_j="61.100000000000001" goal_i="79.800000000000011" goal_j="61.300000000000004" duration="6.1032778078668457"/>
                <section number="5" start_i="79.800000000000011" start_j="61.300000000000004" goal_i="76.800000000000011" goal_j="60.400000000000006" duration="3.1320919526731643"/>
                <section number="6" start_i="76.800000000000011" start_j="60.400000000000006" goal_i="75.700000000000003" goal_j="61.400000000000006" duration="1.4866068747318586"/>
                <section number="7" start_i="75.700000000000003" start_j="61.400000000000006" goal_i="73.600000000000009" goal_j="63.800000000000004" duration="3.1890437438203918"/>
                <section number="8" start_i="73.600000000000009" start_j="63.800000000000004" goal_i="72.100000000000009" goal_j="66.700000000000003" duration="3.2649655434628997"/>
                <section number="9" start_i="72.100000000000009" start_j="66.700000000000003" goal_i="71.900000000000006" goal_j="71.100000000000009" duration="4.4045431091090563"/>
                <section number="10" start_i="71.900000000000006" start_j="71.100000000000009" goal_i="71.600000000000009" goal_j="72.400000000000006" duration="1.3341664064126277"/>
                <section number="11" start_i="71.600000000000009" start_j="72.400000000000006" goal_i="73.100000000000009" goal_j="76.100000000000009" duration="3.9924929555354254"/>
                <section number="12" start_i="73.100000000000009" start_j="76.100000000000009" goal_i="77.200000000000003" goal_j="78.600000000000009" duration="4.802082881417185"/>
                <section number="13" start_i="77.200000000000003" start_j="78.600000000000009" goal_i="82.400000000000006" goal_j="81.700000000000003" duration="6.0539243470661219"/>
                <section number="14" start_i="82.400000000000006" start_j="81.700000000000003" goal_i="83.600000000000009" goal_j="82.400000000000006" duration="1.3892443989449816"/>
                <section number="15" start_i="83.600000000000009" start_j="82.400000000000006" goal_i="97.100000000000009" goal_j="89.200000000000003" duration="15.115885683611126"/>
                <section number="16" start_i="97.100000000000009" start_j="89.200000000000003" goal_i="101.40000000000001" goal_j="91.600000000000009" duration="4.9244289008980502"/>
                <section number="17" start_i="101.40000000000001" start_j="91.600000000000009" goal_i="108.2" goal_j="94.5" duration="7.3925638313104827"/>
                <section number="18" start_i="108.2" start_j="94.5" goal_i="115.90000000000001" goal_j="97.800000000000011" duration="8.3773504164503123"/>
                <section number="19" start_i="115.90000000000001" start_j="97.800000000000011" goal_i="123" goal_j="101.7" duration="8.1006172604314486"/>
                <section number="20" start_i="123" start_j="101.7" goal_i="128.59999999999999" goal_j="104.60000000000001" duration="6.3063460101710263"/>
                <section number="21" start_i="128.59999999999999" start_j="104.60000000000001" goal_i="134.40000000000001" goal_j="107.30000000000001" duration="6.3976558206893372"/>
                <section number="22" start_i="134.40000000000001" start_j="107.30000000000001" goal_i="138.20000000000002" goal_j="108.60000000000001" duration="4.0162171256046548"/>
                <section number="23" start_i="138.20000000000002" start_j="108.60000000000001" goal_i="143" goal_j="110.7" duration="5.2392747589718738"/>
                <section number="24" start_i="143" start_j="110.7" goal_i="148.09999999999999" goal_j="114.10000000000001" duration="6.1294371682887743"/>
                <section number="25" start_i="148.09999999999999" start_j="114.10000000000001" goal_i="150" goal_j="116.40000000000001" duration="2.9832867780352643"/>
                <section number="26" start_i="150" start_j="116.40000000000001" goal_i="154.80000000000001" goal_j="120.80000000000001" duration="6.511528238439908"/>
                <section number="27" start_i="154.80000000000001" start_j="120.80000000000001" goal_i="155.5" goal_j="122.10000000000001" duration="1.4764823060233425"/>
                <section number="28" start_i="155.5" start_j="122.10000000000001" goal_i="157.60000000000002" goal_j="127.90000000000001" duration="6.1684682053164579"/>
                <section number="29" start_i="157.60000000000002" start_j="127.90000000000001" goal_i="159.20000000000002" goal_j="133" duration="5.3450912059570896"/>
                <section number="30" start_i="159.20000000000002" start_j="133" goal_i="159.30000000000001" goal_j="137.09999999999999" duration="4.1012193308819747"/>
                <section number="31" start_i="159.30000000000001" start_j="137.09999999999999" goal_i="153.30000000000001" goal_j="142.90000000000001" duration="8.3450584180100407"/>
                <section number="32" start_i="153.30000000000001" start_j="142.90000000000001" goal_i="144.09999999999999" goal_j="150.20000000000002" duration="11.744360348695039"/>
                <section number="33" start_i="144.09999999999999" start_j="150.20000000000002" goal_i="119.40000000000001" goal_j="157.5" duration="25.756164310704321"/>
                <section number="34" start_i="119.40000000000001" start_j="157.5" goal_i="97.700000000000003" goal_j="165.5" duration="23.127689032845467"/>
                <section number="35" start_i="97.700000000000003" start_j="165.5" goal_i="87.700000000000003" goal_j="168.60000000000002" duration="10.469479452198186"/>
                <section number="36" start_i="87.700000000000003" start_j="168.60000000000002" goal_i="73.5" goal_j="174" duration="15.192103211866339"/>
                <section number="37" start_i="73.5" start_j="174" goal_i="64.5" goal_j="177.20000000000002" duration="9.5519631490076335"/>
                <section number="38" start_i="64.5" start_j="177.20000000000002" goal_i="55.700000000000003" goal_j="180.5" duration="9.3984041198492605"/>
                <section number="39" start_i="55.700000000000003" start_j="180.5" goal_i="52.5" goal_j="180.30000000000001" duration="3.2062439083762797"/>
            </path>
        </agent>
        <agent number="10">
            <path duration="238.1577329840764">
                <section number="0" start_i="65.200000000000003" start_j="138.70000000000002" goal_i="69.600000000000009" goal_j="139.80000000000001" duration="4.5354161881794308"/>
                <section number="1" start_i="69.600000000000009" start_j="139.80000000000001" goal_i="73" goal_j="140.80000000000001" duration="3.5440090293338624"/>
                <section number="2" start_i="73" start_j="140.80000000000001" goal_i="77.400000000000006" goal_j="142.80000000000001" duration="4.8332183894378336"/>
                <section number="3" start_i="77.400000000000006" start_j="142.80000000000001" goal_i="86.300000000000011" goal_j="145.90000000000001" duration="9.4244363226667343"/>
                <section number="4" start_i="86.300000000000011" start_j="145.90000000000001" goal_i="101.60000000000001" goal_j="149.80000000000001" duration="15.789236840328922"/>
                <section number="5" start_i="101.60000000000001" start_j="149.80000000000001" goal_i="106.5" goal_j="151.59999999999999" duration="5.220153254455262"/>
                <section number="6" start_i="106.5" start_j="151.59999999999999" goal_i="109.60000000000001" goal_j="152.80000000000001" duration="3.3241540277189472"/>
                <section number="7" start_i="109.60000000000001" start_j="152.80000000000001" goal_i="113.80000000000001" goal_j="154" duration="4.3680659335683103"/>
                <section number="8" start_i="113.80000000000001" start_j="154" goal_i="117.10000000000001" goal_j="153.40000000000001" duration="3.3541019662496794"/>
                <section number="9" start_i="117.10000000000001" start_j="153.40000000000001" goal_i="124.7" goal_j="152" duration="7.7278716345446554"/>
                <section number="10" start_i="124.7" start_j="152" goal_i="127.2" goal_j="152.09999999999999" duration="2.5019992006393537"/>
                <section number="11" start_i="127.2" start_j="152.09999999999999" goal_i="130.80000000000001" goal_j="151.5" duration="3.649657518178941"/>
                <section number="12" start_i="130.80000000000001" start_j="151.5" goal_i="134.5" goal_j="150.09999999999999" duration="3.9560080889704921"/>
                <section number="13" start_i="134.5" start_j="150.09999999999999" goal_i="137.09999999999999" goal_j="149.40000000000001" duration="2.6925824035672434"/>
                <section number="14" start_i="137.09999999999999" start_j="149.40000000000001" goal_i="146.80000000000001" goal_j="148.20000000000002" duration="9.7739449558507516"/>
                <section number="15" start_i="146.80000000000001" start_j="148.20000000000002" goal_i="153.30000000000001" goal_j="142.90000000000001" duration="8.3868945385047056"/>
                <section number="16" start_i="153.30000000000001" start_j="142.90000000000001" goal_i="159.30000000000001" goal_j="137.09999999999999" duration="8.3450584180100407"/>
                <section number="17" start_i="159.30000000000001" start_j="137.09999999999999" goal_i="159.20000000000002" goal_j="133" duration="4.1012193308819747"/>
                <section number="18" start_i="159.20000000000002" start_j="133" goal_i="157.60000000000002" goal_j="127.90000000000001" duration="5.3450912059571039"/>
                <section number="19" start_i="157.60000000000002" start_j="127.90000000000001" goal_i="155.5" goal_j="122.10000000000001" duration="6.1684682053164579"/>
                <section number="20" start_i="155.5" start_j="122.10000000000001" goal_i="154.80000000000001" goal_j="120.80000000000001" duration="1.4764823060233283"/>
                <section number="21" start_i="154.80000000000001" start_j="120.80000000000001" goal_i="150" goal_j="116.40000000000001" duration="6.5115282384398938"/>
                <section number="22" start_i="150" start_j="116.40000000000001" goal_i="148.09999999999999" goal_j="114.10000000000001" duration="2.9832867780352501"/>
                <section number="23" start_i="148.09999999999999" start_j="114.10000000000001" goal_i="143" goal_j="110.7" duration="6.1294371682887743"/>
                <section number="24" start_i="143" start_j="110.7" goal_i="138.20000000000002" goal_j="108.60000000000001" duration="5.2392747589718738"/>
                <section number="25" start_i="138.20000000000002" start_j="108.60000000000001" goal_i="134.40000000000001" goal_j="107.30000000000001" duration="4.0162171256046406"/>
                <section number="26" start_i="134.40000000000001" start_j="107.30000000000001" goal_i="128.59999999999999" goal_j="104.60000000000001" duration="6.397655820689323"/>
                <section number="27" start_i="128.59999999999999" start_j="104.60000000000001" goal_i="123" goal_j="101.7" duration="6.306346010171012"/>
                <section number="28" start_i="123" start_j="101.7" goal_i="115.90000000000001" goal_j="97.800000000000011" duration="8.1006172604314486"/>
                <section number="29" start_i="115.90000000000001" start_j="97.800000000000011" goal_i="108.2" goal_j="94.5" duration="8.3773504164502981"/>
                <section number="30" start_i="108.2" start_j="94.5" goal_i="101.40000000000001" goal_j="91.600000000000009" duration="7.3925638313104685"/>
                <section number="31" start_i="101.40000000000001" start_j="91.600000000000009" goal_i="97.100000000000009" goal_j="89.200000000000003" duration="4.9244289008980502"/>
                <section number="32" start_i="97.100000000000009" start_j="89.200000000000003" goal_i="83.600000000000009" goal_j="82.400000000000006" duration="15.11588568361114"/>
                <section number="33" start_i="83.600000000000009" start_j="82.400000000000006" goal_i="82.400000000000006" goal_j="81.700000000000003" duration="1.3892443989449816"/>
                <section number="34" start_i="82.400000000000006" start_j="81.700000000000003" goal_i="77.200000000000003" goal_j="78.600000000000009" duration="6.053924347066129"/>
                <section number="35" start_i="77.200000000000003" start_j="78.600000000000009" goal_i="73.100000000000009" goal_j="76.100000000000009" duration="4.8020828814171921"/>
                <section number="36" start_i="73.100000000000009" start_j="76.100000000000009" goal_i="71.600000000000009" goal_j="72.400000000000006" duration="3.9924929555354254"/>
                <section number="37" start_i="71.600000000000009" start_j="72.400000000000006" goal_i="71.900000000000006" goal_j="71.100000000000009" duration="1.3341664064126348"/>
                <section number="38" start_i="71.900000000000006" start_j="71.100000000000009" goal_i="72.100000000000009" goal_j="66.700000000000003" duration="4.4045431091090563"/>
                <section number="39" start_i="72.100000000000009" start_j="66.700000000000003" goal_i="73.600000000000009" goal_j="63.800000000000004" duration="3.2649655434628926"/>
                <section number="40" start_i="73.600000000000009" start_j="63.800000000000004" goal_i="75.700000000000003" goal_j="61.400000000000006" duration="3.1890437438203776"/>
                <section number="41" start_i="75.700000000000003" start_j="61.400000000000006" goal_i="76.800000000000011" goal_j="60.400000000000006" duration="1.4866068747318479"/>
                <section number="42" start_i="76.800000000000011" start_j="60.400000000000006" goal_i="84.700000000000003" goal_j="62.700000000000003" duration="8.2280009722896637"/>
            </path>
        </agent>
        <agent number="11">
            <path duration="102.91939283809002">
                <section number="0" start_i="139.70000000000002" start_j="180.5" goal_i="149.40000000000001" goal_j="163.5" duration="19.572685048301366"/>
                <section number="1" start_i="149.40000000000001" start_j="163.5" goal_i="155.20000000000002" goal_j="155.40000000000001" duration="9.9624294225856396"/>
                <section number="2" start_i="155.20000000000002" start_j="155.40000000000001" goal_i="158.60000000000002" goal_j="146.59999999999999" duration="9.4339811320566191"/>
                <section number="3" start_i="158.60000000000002" start_j="146.59999999999999" goal_i="162.70000000000002" goal_j="138" duration="9.5273291115611158"/>
                <section number="4" start_i="162.70000000000002" start_j="138" goal_i="165.20000000000002" goal_j="133" duration="5.5901699437494727"/>
                <section number="5" start_i="165.20000000000002" start_j="133" goal_i="167.70000000000002" goal_j="128.20000000000002" duration="5.4120236510939108"/>
                <section number="6" start_i="167.70000000000002" start_j="128.20000000000002" goal_i="170.30000000000001" goal_j="123.80000000000001" duration="5.1107729356722515"/>
                <section number="7" start_i="170.30000000000001" start_j="123.80000000000001" goal_i="172.5" goal_j="118.90000000000001" duration="5.3712196007983124"/>
                <section number="8" start_i="172.5" start_j="118.90000000000001" goal_i="182.10000000000002" goal_j="102.2" duration="19.262658175859343"/>
                <section number="9" start_i="182.10000000000002" start_j="102.2" goal_i="185.30000000000001" goal_j="96.300000000000011" duration="6.7119296778199242"/>
                <section number="10" start_i="185.30000000000001" start_j="96.300000000000011" goal_i="189" goal_j="90.400000000000006" duration="6.9641941385920632"/>
            </path>
        </agent>
        <agent number="12">
            <path duration="156.25240249226911">
                <section number="0" start_i="60.300000000000004" start_j="161.20000000000002" goal_i="67" goal_j="161.30000000000001" duration="6.7007462271003773"/>
                <section number="1" start_i="67" start_j="161.30000000000001" goal_i="68.299999999999997" goal_j="161.10000000000002" duration="1.3152946437965864"/>
                <section number="2" start_i="68.299999999999997" start_j="161.10000000000002" goal_i="75.799999999999997" goal_j="160.30000000000001" duration="7.5425459892532327"/>
                <section number="3" start_i="75.799999999999997" start_j="160.30000000000001" goal_i="81.600000000000009" goal_j="160.20000000000002" duration="5.8008620049092805"/>
                <section number="4" start_i="81.600000000000009" start_j="160.20000000000002" goal_i="84" goal_j="160.20000000000002" duration="2.3999999999999915"/>
                <section number="5" start_i="84" start_j="160.20000000000002" goal_i="89.400000000000006" goal_j="159.20000000000002" duration="5.4918120870983991"/>
                <section number="6" start_i="89.400000000000006" start_j="159.20000000000002" goal_i="93.100000000000009" goal_j="158.70000000000002" duration="3.7336309405188963"/>
                <section number="7" start_i="93.100000000000009" start_j="158.70000000000002" goal_i="101.10000000000001" goal_j="157.30000000000001" duration="8.1215762016987796"/>
                <section number="8" start_i="101.10000000000001" start_j="157.30000000000001" goal_i="105" goal_j="156.30000000000001" duration="4.0261644278394684"/>
                <section number="9" start_i="105" start_j="156.30000000000001" goal_i="110.90000000000001" goal_j="155.10000000000002" duration="6.0207972893961497"/>
                <section number="10" start_i="110.90000000000001" start_j="155.10000000000002" goal_i="117.90000000000001" goal_j="154.30000000000001" duration="7.0455659815234171"/>
                <section number="11" start_i="117.90000000000001" start_j="154.30000000000001" goal_i="121.2" goal_j="153.60000000000002" duration="3.3734255586865984"/>
                <section number="12" start_i="121.2" start_j="153.60000000000002" goal_i="126.7" goal_j="153" duration="5.5326304774492172"/>
                <section number="13" start_i="126.7" start_j="153" goal_i="138.20000000000002" goal_j="151.20000000000002" duration="11.640017182117916"/>
                <section number="14" start_i="138.20000000000002" start_j="151.20000000000002" goal_i="146.80000000000001" goal_j="148.20000000000002" duration="9.1082380293885592"/>
                <section number="15" start_i="146.80000000000001" start_j="148.20000000000002" goal_i="153.30000000000001" goal_j="142.90000000000001" duration="8.3868945385047056"/>
                <section number="16" start_i="153.30000000000001" start_j="142.90000000000001" goal_i="159.30000000000001" goal_j="137.09999999999999" duration="8.3450584180100407"/>
                <section number="17" start_i="159.30000000000001" start_j="137.09999999999999" goal_i="165.10000000000002" goal_j="127.2" duration="11.473883387938017"/>
                <section number="18" start_i="165.10000000000002" start_j="127.2" goal_i="171.40000000000001" goal_j="116" duration="12.850291825480056"/>
                <section number="19" start_i="171.40000000000001" start_j="116" goal_i="176.90000000000001" goal_j="106.5" duration="10.977249200050068"/>
                <section number="20" start_i="176.90000000000001" start_j="106.5" goal_i="183.30000000000001" goal_j="96.800000000000011" duration="11.621101496846165"/>
                <section number="21" start_i="183.30000000000001" start_j="96.800000000000011" goal_i="186.70000000000002" goal_j="94.800000000000011" duration="3.9446165846632084"/>
                <section number="22" start_i="186.70000000000002" start_j="94.800000000000011" goal_i="187.5" goal_j="94.800000000000011" duration="0.79999999999998295"/>
            </path>
        </agent>
        <agent number="13">
            <path duration="228.78279606293057">
                <section number="0" start_i="244" start_j="45.5" goal_i="240.40000000000001" goal_j="47.900000000000006" duration="4.3266615305567857"/>
                <section number="1" start_i="240.40000000000001" start_j="47.900000000000006" goal_i="237.5" goal_j="50" duration="3.5805027579936324"/>
                <section number="2" start_i="237.5" start_j="50" goal_i="234" goal_j="53" duration="4.6097722286464426"/>
                <section number="3" start_i="234" start_j="53" goal_i="230.70000000000002" goal_j="54.900000000000006" duration="3.8078865529319401"/>
                <section number="4" start_i="230.70000000000002" start_j="54.900000000000006" goal_i="226.60000000000002" goal_j="55.800000000000004" duration="4.1976183723630669"/>
                <section number="5" start_i="226.60000000000002" start_j="55.800000000000004" goal_i="221.40000000000001" goal_j="56.200000000000003" duration="5.215361924162135"/>
                <section number="6" start_i="221.40000000000001" start_j="56.200000000000003" goal_i="205.80000000000001" goal_j="56.600000000000001" duration="15.60512736250492"/>
                <section number="7" start_i="205.80000000000001" start_j="56.600000000000001" goal_i="190.40000000000001" goal_j="56.700000000000003" duration="15.400324671902219"/>
                <section number="8" start_i="190.40000000000001" start_j="56.700000000000003" goal_i="173.70000000000002" goal_j="56.700000000000003" duration="16.699999999999982"/>
                <section number="9" start_i="173.70000000000002" start_j="56.700000000000003" goal_i="161.20000000000002" goal_j="53.5" duration="12.903100402616417"/>
                <section number="10" start_i="161.20000000000002" start_j="53.5" goal_i="159.20000000000002" goal_j="53" duration="2.0615528128088272"/>
                <section number="11" start_i="159.20000000000002" start_j="53" goal_i="153.90000000000001" goal_j="50.600000000000001" duration="5.8180752831155473"/>
                <section number="12" start_i="153.90000000000001" start_j="50.600000000000001" goal_i="148.59999999999999" goal_j="48.600000000000001" duration="5.6648036153074344"/>
                <section number="13" start_i="148.59999999999999" start_j="48.600000000000001" goal_i="145.30000000000001" goal_j="48.900000000000006" duration="3.3136083051561656"/>
                <section number="14" start_i="145.30000000000001" start_j="48.900000000000006" goal_i="145" goal_j="48.400000000000006" duration="0.58309518948453842"/>
                <section number="15" start_i="145" start_j="48.400000000000006" goal_i="138.80000000000001" goal_j="47.100000000000001" duration="6.3348243858847297"/>
                <section number="16" start_i="138.80000000000001" start_j="47.100000000000001" goal_i="130.70000000000002" goal_j="49.600000000000001" duration="8.4770277810090988"/>
                <section number="17" start_i="130.70000000000002" start_j="49.600000000000001" goal_i="124.60000000000001" goal_j="52.200000000000003" duration="6.6309878600401646"/>
                <section number="18" start_i="124.60000000000001" start_j="52.200000000000003" goal_i="120.10000000000001" goal_j="52.5" duration="4.5099889135118758"/>
                <section number="19" start_i="120.10000000000001" start_j="52.5" goal_i="105.7" goal_j="54" duration="14.477914214416387"/>
                <section number="20" start_i="105.7" start_j="54" goal_i="101.10000000000001" goal_j="56.200000000000003" duration="5.0990195135927934"/>
                <section number="21" start_i="101.10000000000001" start_j="56.200000000000003" goal_i="99.300000000000011" goal_j="56.400000000000006" duration="1.8110770276274764"/>
                <section number="22" start_i="99.300000000000011" start_j="56.400000000000006" goal_i="96.100000000000009" goal_j="56.600000000000001" duration="3.2062439083762797"/>
                <section number="23" start_i="96.100000000000009" start_j="56.600000000000001" goal_i="92.700000000000003" goal_j="56.600000000000001" duration="3.4000000000000057"/>
                <section number="24" start_i="92.700000000000003" start_j="56.600000000000001" goal_i="86.400000000000006" goal_j="58.100000000000001" duration="6.476109943476871"/>
                <section number="25" start_i="86.400000000000006" start_j="58.100000000000001" goal_i="76.800000000000011" goal_j="60.400000000000006" duration="9.8716766559688267"/>
                <section number="26" start_i="76.800000000000011" start_j="60.400000000000006" goal_i="66.400000000000006" goal_j="64.299999999999997" duration="11.107204868912788"/>
                <section number="27" start_i="66.400000000000006" start_j="64.299999999999997" goal_i="59" goal_j="67.600000000000009" duration="8.1024687595818818"/>
                <section number="28" start_i="59" start_j="67.600000000000009" goal_i="51.300000000000004" goal_j="69.100000000000009" duration="7.8447434629820805"/>
                <section number="29" start_i="51.300000000000004" start_j="69.100000000000009" goal_i="45.700000000000003" goal_j="70.700000000000003" duration="5.8240879114244137"/>
                <section number="30" start_i="45.700000000000003" start_j="70.700000000000003" goal_i="39.600000000000001" goal_j="72.799999999999997" duration="6.4513564465157174"/>
                <section number="31" start_i="39.600000000000001" start_j="72.799999999999997" goal_i="37.200000000000003" goal_j="73.299999999999997" duration="2.4515301344262639"/>
                <section number="32" start_i="37.200000000000003" start_j="73.299999999999997" goal_i="32.300000000000004" goal_j="74.299999999999997" duration="5.0009999000199912"/>
                <section number="33" start_i="32.300000000000004" start_j="74.299999999999997" goal_i="31.5" goal_j="74.600000000000009" duration="0.85440037453176387"/>
                <section number="34" start_i="31.5" start_j="74.600000000000009" goal_i="27.900000000000002" goal_j="76.200000000000003" duration="3.9395431207184402"/>
                <section number="35" start_i="27.900000000000002" start_j="76.200000000000003" goal_i="25.900000000000002" goal_j="78.600000000000009" duration="3.1240998703626701"/>
            </path>
        </agent>
    </log>
</root>
